modules/Data_Memory.v
module DataMemory (
    input clk,                      // clock signal
    input write_enable,             // enabling signal for writing Data Memory
    input [31:0] address,            // Take address of memory to read/write value
    input [31:0] write_data,        // data to write to Data Memory
    input [3:0] write_mask,         // bitmask for writing data (Should receive 4'b1111 in RV32I47F and 50F top module)

    input [31:0] rom_read_data,
    output [31:0] rom_address,

    output reg [31:0] read_data    // data read from Data Memory
);

    reg [31:0] memory [0:1023];     // 1024 words (4KB), FPGA is 32KB = 8192 (0:8191)
    reg [31:0] new_word;
    
    // 32 bit extended mask from 4 bit write_mask
    wire [31:0] extended_mask = {{8{write_mask[3]}}, {8{write_mask[2]}}, {8{write_mask[1]}}, {8{write_mask[0]}}};
    wire ram_access = (address[31:16] == 16'h1000);
    wire rom_access = (address[31:16] == 16'h0000);
    wire [12:0] ram_address = address[14:2];
    assign rom_address = address;

    integer i;
    initial begin
        for (i=0; i<1024; i=i+1) begin
            memory[i] = 32'b0;
        end // $readmemh("./data_init.mem", memory, 13'h1424);
        new_word = 32'b0;
    end

    always @(*) begin
        if (ram_access) begin
            read_data = memory[ram_address];
        end else if (rom_access) begin
            read_data = rom_read_data;
        end else begin
            read_data = 32'b0; // for wrong address
        end
        
    end

    always @(posedge clk) begin
        if (write_enable && ram_access) begin
            new_word = ((memory[ram_address] & ~extended_mask) | (write_data & extended_mask));
            memory[ram_address] <= new_word;
        end
    end

endmodule

testbenches/Data_Memory_tb.v
`timescale 1ns/1ps

module DataMemory_tb;
    reg clk;
    reg write_enable;
    reg [31:0] address;
    reg [31:0] write_data;
    reg [3:0] write_mask;
    reg [31:0] rom_read_data;

    wire [31:0] read_data;
    wire [31:0] rom_address;

    DataMemory data_memory (
        .clk(clk),
        .write_enable(write_enable),
        .address(address),
        .write_data(write_data),
        .write_mask(write_mask),
        .rom_read_data(rom_read_data),
        .rom_address(rom_address),
        .read_data(read_data)
    );

    // Generate clock signal (period = 10ns)
    always #5 clk = ~clk;

    initial begin
        $dumpfile("testbenches/results/waveforms/Data_Memory_tb_result.vcd");
        $dumpvars(0, data_memory);

        $display("==================== Data Memory Test START ====================");

        // Initialize signals
        clk = 0;
        write_enable = 0;
        address = 32'h00000000;
        write_data = 32'h00000000;
        write_mask = 4'b0000;
        rom_read_data = 32'h00000000;

        // ========================================================================
        // Test 1: ROM Address Region Test (0x0000xxxx)
        // ========================================================================
        $display("\n[Test 1] ROM Address Region Read (0x0000xxxx):");
        
        // ROM access should output rom_address and use rom_read_data as read_data
        address = 32'h00000004;
        rom_read_data = 32'h12345678;
        #10;
        $display("  address=%h, rom_address=%h, rom_read_data=%h, read_data=%h", 
                 address, rom_address, rom_read_data, read_data);
        $display("  -> Expected: rom_address=00000004, read_data=12345678 (from ROM)");
        
        address = 32'h00001000;
        rom_read_data = 32'hABCDEF01;
        #10;
        $display("  address=%h, rom_address=%h, rom_read_data=%h, read_data=%h", 
                 address, rom_address, rom_read_data, read_data);
        $display("  -> Expected: rom_address=00001000, read_data=ABCDEF01 (from ROM)");
        
        address = 32'h0000FFFC;
        rom_read_data = 32'hCAFEBABE;
        #10;
        $display("  address=%h, rom_address=%h, rom_read_data=%h, read_data=%h", 
                 address, rom_address, rom_read_data, read_data);
        $display("  -> Expected: rom_address=0000FFFC, read_data=CAFEBABE (from ROM)");

        // ========================================================================
        // Test 2: RAM Address Region Initialization (0x1000xxxx)
        // ========================================================================
        $display("\n[Test 2] RAM Address Region Initialization (0x1000xxxx):");

        address = 32'h10000004;
        rom_read_data = 32'hDEADBEEF;  // Should be ignored in RAM region
        #10;
        $display("  address=%h, rom_read_data=%h (ignored), read_data=%h", 
                 address, rom_read_data, read_data);
        $display("  -> Expected: read_data=00000000 (RAM initialized to 0)");
        
        // ========================================================================
        // Test 3: RAM Full Write and Read (0x1000xxxx)
        // ========================================================================
        $display("\n[Test 3] RAM Full Write and Read:");

        address = 32'h10000004;
        write_data = 32'hDEADBEEF;
        write_mask = 4'b1111;
        write_enable = 1;
        rom_read_data = 32'h12345678;  // Should be ignored in RAM region
        #10;
        
        write_enable = 0;
        #10;
        
        $display("  address=%h, write_data=%h, mask=%b, read_data=%h", 
                 address, write_data, write_mask, read_data);
        $display("  -> Expected: read_data=DEADBEEF (written to RAM, ROM data ignored)");

        // ========================================================================
        // Test 4: RAM Partial Write (Byte Masking)
        // ========================================================================
        $display("\n[Test 4] RAM Partial Write (Byte Masking):");

        // Write to MSB only (mask = 1000)
        write_data = 32'hCAFECAFE;
        write_mask = 4'b1000;
        write_enable = 1;
        #10;
        
        write_enable = 0;
        #10;
        
        $display("  mask=1000: address=%h, write_data=%h, read_data=%h", 
                 address, write_data, read_data);
        $display("  -> Expected: read_data=CAADBEEF (only byte[31:24] changed)");

        // Write to byte[23:16] (mask = 0100)
        write_data = 32'hCAFECAFE;
        write_mask = 4'b0100;
        write_enable = 1;
        #10;
        
        write_enable = 0;
        #10;
        
        $display("  mask=0100: address=%h, write_data=%h, read_data=%h", 
                 address, write_data, read_data);
        $display("  -> Expected: read_data=CAFEBEEF (only byte[23:16] changed)");

        // Write to byte[15:8] (mask = 0010)
        write_data = 32'hCAFECAFE;
        write_mask = 4'b0010;
        write_enable = 1;
        #10;
        
        write_enable = 0;
        #10;
        
        $display("  mask=0010: address=%h, write_data=%h, read_data=%h", 
                 address, write_data, read_data);
        $display("  -> Expected: read_data=CAFECAEF (only byte[15:8] changed)");

        // Write to LSB only (mask = 0001)
        write_data = 32'hCAFECAFE;
        write_mask = 4'b0001;
        write_enable = 1;
        #10;
        
        write_enable = 0;
        #10;
        
        $display("  mask=0001: address=%h, write_data=%h, read_data=%h", 
                 address, write_data, read_data);
        $display("  -> Expected: read_data=CAFECAFE (only byte[7:0] changed)");

        // Write upper half-word (mask = 1100)
        write_data = 32'hDEADBEEF;
        write_mask = 4'b1100;
        write_enable = 1;
        #10;
        
        write_enable = 0;
        #10;
        
        $display("  mask=1100: address=%h, write_data=%h, read_data=%h", 
                 address, write_data, read_data);
        $display("  -> Expected: read_data=DEADCAFE (upper half-word changed)");

        // Write lower half-word (mask = 0011)
        write_data = 32'hDEADBEEF;
        write_mask = 4'b0011;
        write_enable = 1;
        #10;
        
        write_enable = 0;
        #10;
        
        $display("  mask=0011: address=%h, write_data=%h, read_data=%h", 
                 address, write_data, read_data);
        $display("  -> Expected: read_data=DEADBEEF (lower half-word changed)");

        // ========================================================================
        // Test 5: RAM Multiple Address Write/Read
        // ========================================================================
        $display("\n[Test 5] RAM Multiple Address Write/Read:");

        address = 32'h10000014;
        write_data = 32'h19721121;
        write_mask = 4'b1111;
        write_enable = 1;
        #10;
        
        write_enable = 0;
        #10;
        
        $display("  address=%h, write_data=%h, mask=%b, read_data=%h", 
                 address, write_data, write_mask, read_data);

        // Read from previously written address (0x10000004)
        address = 32'h10000004;
        #10;
        $display("  address=%h (previous), read_data=%h", address, read_data);
        $display("  -> Expected: read_data=DEADBEEF (previously written)");

        // ========================================================================
        // Test 6: Address Region Boundary Test
        // ========================================================================
        $display("\n[Test 6] Address Region Boundary Test:");
        
        // ROM region upper boundary (0x0000FFFF)
        address = 32'h0000FFFC;
        rom_read_data = 32'hFFFFFFFF;
        write_enable = 0;
        #10;
        $display("  ROM boundary: address=%h, rom_address=%h, read_data=%h", 
                 address, rom_address, read_data);
        $display("  -> Expected: read_data=FFFFFFFF (from ROM)");
        
        // RAM region lower boundary (0x10000000)
        address = 32'h10000000;
        write_data = 32'h11111111;
        write_mask = 4'b1111;
        write_enable = 1;
        #10;
        write_enable = 0;
        #10;
        $display("  RAM boundary: address=%h, write_data=%h, read_data=%h", 
                 address, write_data, read_data);
        $display("  -> Expected: read_data=11111111 (written to RAM)");

        // ========================================================================
        // Test 7: Invalid Address Region (not ROM or RAM)
        // ========================================================================
        $display("\n[Test 7] Invalid Address Region:");
        
        address = 32'h20000000;  // Invalid region
        rom_read_data = 32'h12345678;
        #10;
        $display("  address=%h, rom_read_data=%h, read_data=%h", 
                 address, rom_read_data, read_data);
        $display("  -> Expected: read_data=00000000 (invalid address returns 0)");
        
        address = 32'hFFFFFFFF;  // Invalid region
        #10;
        $display("  address=%h, read_data=%h", address, read_data);
        $display("  -> Expected: read_data=00000000 (invalid address returns 0)");

        // ========================================================================
        // Test 8: ROM vs RAM Read Priority Test
        // ========================================================================
        $display("\n[Test 8] ROM vs RAM Read Priority:");
        
        // Write to RAM address
        address = 32'h10000020;
        write_data = 32'hAAAAAAAA;
        write_mask = 4'b1111;
        write_enable = 1;
        #10;
        write_enable = 0;
        #10;
        $display("  RAM write: address=%h, write_data=%h, read_data=%h", 
                 address, write_data, read_data);
        
        // Switch to ROM address with different data
        address = 32'h00000020;
        rom_read_data = 32'hBBBBBBBB;
        #10;
        $display("  ROM read:  address=%h, rom_read_data=%h, read_data=%h", 
                 address, rom_read_data, read_data);
        $display("  -> Expected: read_data=BBBBBBBB (ROM data, not RAM data)");

        // ========================================================================
        // Test 9: RAM Write Enable Control
        // ========================================================================
        $display("\n[Test 9] RAM Write Enable Control:");

        address = 32'h10000024;
        write_data = 32'hDEADBEEF;
        write_mask = 4'b1111;
        write_enable = 0;  // Write disabled
        #10;
        
        $display("  write_enable=0: address=%h, write_data=%h, read_data=%h", 
                 address, write_data, read_data);
        $display("  -> Expected: read_data=00000000 (write not performed)");
        
        write_enable = 1;  // Write enabled
        #10;
        write_enable = 0;
        #10;
        
        $display("  write_enable=1: address=%h, write_data=%h, read_data=%h", 
                 address, write_data, read_data);
        $display("  -> Expected: read_data=DEADBEEF (write performed)");

        // ========================================================================
        // Test 10: ROM Address Output Verification
        // ========================================================================
        $display("\n[Test 10] ROM Address Output Verification:");
        
        address = 32'h00000100;
        #10;
        $display("  address=%h, rom_address=%h", address, rom_address);
        $display("  -> Expected: rom_address=00000100 (same as input address)");
        
        address = 32'h00002000;
        #10;
        $display("  address=%h, rom_address=%h", address, rom_address);
        $display("  -> Expected: rom_address=00002000 (same as input address)");

        $display("\n====================  Data Memory Test END  ====================");
        $stop;
    end

endmodule

testbenches/results/waveforms/Data_Memory_tb_result.vcd
$date
	Sat Dec 13 20:29:33 2025
$end
$version
	Icarus Verilog
$end
$timescale
	1ps
$end
$scope module DataMemory_tb $end
$scope module data_memory $end
$var wire 32 ! address [31:0] $end
$var wire 1 " clk $end
$var wire 32 # rom_address [31:0] $end
$var wire 32 $ rom_read_data [31:0] $end
$var wire 32 % write_data [31:0] $end
$var wire 1 & write_enable $end
$var wire 4 ' write_mask [3:0] $end
$var wire 1 ( rom_access $end
$var wire 13 ) ram_address [12:0] $end
$var wire 1 * ram_access $end
$var wire 32 + extended_mask [31:0] $end
$var reg 32 , new_word [31:0] $end
$var reg 32 - read_data [31:0] $end
$var integer 32 . i [31:0] $end
$upscope $end
$upscope $end
$enddefinitions $end
$comment Show the parameter values. $end
$dumpall
$end
#0
$dumpvars
b10000000000 .
b10010001101000101011001111000 -
bx ,
b0 +
0*
b1 )
1(
b0 '
0&
b0 %
b10010001101000101011001111000 $
b100 #
0"
b100 !
$end
#5000
1"
#10000
b10101011110011011110111100000001 -
b10000000000 )
0"
b10101011110011011110111100000001 $
b1000000000000 #
b1000000000000 !
#15000
1"
#20000
b11001010111111101011101010111110 -
b1111111111111 )
0"
b11001010111111101011101010111110 $
b1111111111111100 #
b1111111111111100 !
#25000
1"
#30000
b0 -
1*
0(
b1 )
0"
b11011110101011011011111011101111 $
b10000000000000000000000000100 #
b10000000000000000000000000100 !
#35000
1"
#40000
b11111111111111111111111111111111 +
0"
b10010001101000101011001111000 $
1&
b1111 '
b11011110101011011011111011101111 %
#45000
b11011110101011011011111011101111 -
b11011110101011011011111011101111 ,
1"
#50000
0"
0&
#55000
1"
#60000
b11111111000000000000000000000000 +
0"
1&
b1000 '
b11001010111111101100101011111110 %
#65000
b11001010101011011011111011101111 -
b11001010101011011011111011101111 ,
1"
#70000
0"
0&
#75000
1"
#80000
b111111110000000000000000 +
0"
1&
b100 '
#85000
b11001010111111101011111011101111 -
b11001010111111101011111011101111 ,
1"
#90000
0"
0&
#95000
1"
#100000
b1111111100000000 +
0"
1&
b10 '
#105000
b11001010111111101100101011101111 -
b11001010111111101100101011101111 ,
1"
#110000
0"
0&
#115000
1"
#120000
b11111111 +
0"
1&
b1 '
#125000
b11001010111111101100101011111110 -
b11001010111111101100101011111110 ,
1"
#130000
0"
0&
#135000
1"
#140000
b11111111111111110000000000000000 +
0"
1&
b1100 '
b11011110101011011011111011101111 %
#145000
b11011110101011011100101011111110 -
b11011110101011011100101011111110 ,
1"
#150000
0"
0&
#155000
1"
#160000
b1111111111111111 +
0"
1&
b11 '
#165000
b11011110101011011011111011101111 -
b11011110101011011011111011101111 ,
1"
#170000
0"
0&
#175000
1"
#180000
b0 -
b11111111111111111111111111111111 +
b101 )
0"
1&
b1111 '
b11001011100100001000100100001 %
b10000000000000000000000010100 #
b10000000000000000000000010100 !
#185000
b11001011100100001000100100001 -
b11001011100100001000100100001 ,
1"
#190000
0"
0&
#195000
1"
#200000
b11011110101011011011111011101111 -
b1 )
0"
b10000000000000000000000000100 #
b10000000000000000000000000100 !
#205000
1"
#210000
b11111111111111111111111111111111 -
0*
1(
b1111111111111 )
0"
b11111111111111111111111111111111 $
b1111111111111100 #
b1111111111111100 !
#215000
1"
#220000
b0 -
1*
0(
b0 )
0"
1&
b10001000100010001000100010001 %
b10000000000000000000000000000 #
b10000000000000000000000000000 !
#225000
b10001000100010001000100010001 -
b10001000100010001000100010001 ,
1"
#230000
0"
0&
#235000
1"
#240000
b0 -
0*
0"
b10010001101000101011001111000 $
b100000000000000000000000000000 #
b100000000000000000000000000000 !
#245000
1"
#250000
b1111111111111 )
0"
b11111111111111111111111111111111 #
b11111111111111111111111111111111 !
#255000
1"
#260000
1*
b1000 )
0"
1&
b10101010101010101010101010101010 %
b10000000000000000000000100000 #
b10000000000000000000000100000 !
#265000
b10101010101010101010101010101010 -
b10101010101010101010101010101010 ,
1"
#270000
0"
0&
#275000
1"
#280000
b10111011101110111011101110111011 -
0*
1(
0"
b10111011101110111011101110111011 $
b100000 #
b100000 !
#285000
1"
#290000
b0 -
1*
0(
b1001 )
0"
b11011110101011011011111011101111 %
b10000000000000000000000100100 #
b10000000000000000000000100100 !
#295000
1"
#300000
0"
1&
#305000
b11011110101011011011111011101111 -
b11011110101011011011111011101111 ,
1"
#310000
0"
0&
#315000
1"
#320000
b10111011101110111011101110111011 -
0*
1(
b1000000 )
0"
b100000000 #
b100000000 !
#325000
1"
#330000
b100000000000 )
0"
b10000000000000 #
b10000000000000 !
