RV32I/modules/EX_MEM_Register.v
module EX_MEM_Register #(
    parameter XLEN = 32
)(
    // pipeline register control signals
    input wire clk,
    input wire reset,
    input wire flush,

    // signals from ID/EX register
    input wire [XLEN-1:0] EX_pc_plus_4,

    input wire EX_memory_read,
    input wire EX_memory_write,
    input wire [2:0] EX_register_file_write_data_select,
    input wire [6:0] EX_opcode,
    input wire [2:0] EX_funct3,
    input wire [XLEN-1:0] EX_read_data2, // Register File to Data Memory read data
    input wire [XLEN-1:0] EX_imm,
    input wire [XLEN-1:0] EX_csr_read_data,

    // signals from EX phase
    input wire [XLEN-1:0] EX_alu_result,

    // signals to EX/MEM register
    output reg [XLEN-1:0] MEM_pc_plus_4,

    output reg MEM_memory_read,
    output reg MEM_memory_write,
    output reg [2:0] MEM_register_file_write_data_select,
    output reg [6:0] MEM_opcode,
    output reg [2:0] MEM_funct3,
    output reg [XLEN-1:0] MEM_read_data2,
    output reg [XLEN-1:0] MEM_imm,
    output reg [XLEN-1:0] MEM_csr_read_data,

    output reg [XLEN-1:0] MEM_alu_result
);

always @(posedge clk or posedge reset) begin
    if (reset || flush) begin
        MEM_pc_plus_4 <= {XLEN{1'b0}};

        MEM_memory_read <= 1'b0;
        MEM_memory_write <= 1'b0;
        MEM_register_file_write_data_select <= 3'b0;
        MEM_opcode <= 7'b0;
        MEM_funct3 <= 3'b0;
        MEM_read_data2 <= {XLEN{1'b0}};
        MEM_imm <= {XLEN{1'b0}};
        MEM_csr_read_data <= {XLEN{1'b0}};

        MEM_alu_result <= {XLEN{1'b0}};
    end else begin
        MEM_pc_plus_4 <= EX_pc_plus_4;

        MEM_memory_read <= EX_memory_read;
        MEM_memory_write <= EX_memory_write;
        MEM_register_file_write_data_select <= EX_register_file_write_data_select;
        MEM_opcode <= EX_opcode;
        MEM_funct3 <= EX_funct3;
        MEM_read_data2 <= EX_read_data2;
        MEM_imm <= EX_imm;
        MEM_csr_read_data <= EX_csr_read_data;
    end
end

endmodule

RV32I/testbenches/EX_MEM_Register_tb.v
`timescale 1ns/1ps

module EX_MEM_Register_tb;
    localparam XLEN = 32;

    reg clk = 0;
    reg reset = 0;
    reg flush = 0;

    reg [XLEN-1:0] EX_pc_plus_4;

    reg EX_memory_read;
    reg EX_memory_write;
    reg [2:0] EX_register_file_write_data_select;
    reg [6:0] EX_opcode; 
    reg [2:0] EX_funct3;
    reg [XLEN-1:0] EX_read_data2;
    reg [XLEN-1:0] EX_imm;
    reg [XLEN-1:0] EX_csr_read_data;

    reg [XLEN-1:0] EX_alu_result;

    wire [XLEN-1:0] MEM_pc_plus_4;

    wire MEM_memory_read;
    wire MEM_memory_write;
    wire [2:0] MEM_register_file_write_data_select;
    wire [6:0] MEM_opcode;
    wire [2:0] MEM_funct3;
    wire [XLEN-1:0] MEM_read_data2;
    wire [XLEN-1:0] MEM_imm;
    wire [XLEN-1:0] MEM_csr_read_data;

    wire [XLEN-1:0] MEM_alu_result;

    EX_MEM_Register #(.XLEN(32)) ex_mem_register (
        .clk(clk),
		.reset(reset),
        .flush(flush),

        .EX_pc_plus_4(EX_pc_plus_4),

        .EX_memory_read(EX_memory_read),
        .EX_memory_write(EX_memory_write),
        .EX_register_file_write_data_select(EX_register_file_write_data_select),
        .EX_opcode(EX_opcode),
        .EX_funct3(EX_funct3),
        .EX_read_data2(EX_read_data2),
        .EX_imm(EX_imm),
        .EX_csr_read_data(EX_csr_read_data),

        .EX_alu_result(EX_alu_result),

        .MEM_pc_plus_4(MEM_pc_plus_4),

        .MEM_memory_read(MEM_memory_read),
        .MEM_memory_write(MEM_memory_write),
        .MEM_register_file_write_data_select(MEM_register_file_write_data_select),
        .MEM_opcode(MEM_opcode),
        .MEM_funct3(MEM_funct3),
        .MEM_read_data2(MEM_read_data2),
        .MEM_imm(MEM_imm),
        .MEM_csr_read_data(MEM_csr_read_data),

        .MEM_alu_result(MEM_alu_result)
    );

    always #5 clk = ~clk;

    initial begin
        $dumpfile("testbenches/results/waveforms/EX_MEM_Register_tb_result.vcd");
        $dumpvars(0, EX_MEM_Register_tb.ex_mem_register);

        // Test sequence
        $display("==================== EX_MEM Register Test START ====================\n");

        // reset
        reset = 1'b1;
        #30;
        reset = 1'b0;
        @(posedge clk);
        $display("Input now");
        $display("|     PC+4     | MEMread | MEMwrite | RF_WD select |  opcode  | funct3 |");
        $display("|   %h   |    %b    |     %b    |      %b     |  %b  |  %b  |", MEM_pc_plus_4, MEM_memory_read, MEM_memory_write, MEM_register_file_write_data_select, MEM_opcode, MEM_funct3);
        $display("| Register RD2 |    imm    | csr_read_data |   ALU result   |");
        $display("|   %h   |  %h |   %h    |    %h    |\n", MEM_read_data2, MEM_imm, MEM_csr_read_data, MEM_alu_result);
        #10;
        
        // Test 1
        @(negedge clk); 
        EX_pc_plus_4               = 32'h0000_0008;   // (PC+4)
        EX_memory_read             = 1'b0;
        EX_memory_write            = 1'b1;            // Store
        EX_register_file_write_data_select = 3'b000;  // don't-care (store)
        EX_opcode                  = 7'b0100011;      // STORE opcode
        EX_funct3                  = 3'b010;          // SW
        EX_read_data2              = 32'hDEAD_BEEF;   // Write Data
        EX_imm                     = 32'h0000_0010;   // offset 16
        EX_csr_read_data           = 32'h0000_0000;   // no CSR
        EX_alu_result              = 32'h1000_0040;   // Calculation result = x3 + 16

        @(posedge clk); #1;
        $display("Test 1: Previous value should be output now");
        $display("|     PC+4     | MEMread | MEMwrite | RF_WD select |  opcode  | funct3 |");
        $display("|   %h   |    %b    |     %b    |      %b     |  %b  |  %b  |", MEM_pc_plus_4, MEM_memory_read, MEM_memory_write, MEM_register_file_write_data_select, MEM_opcode, MEM_funct3);
        $display("| Register RD2 |    imm    | csr_read_data |   ALU result   |");
        $display("|   %h   |  %h |   %h    |    %h    |\n", MEM_read_data2, MEM_imm, MEM_csr_read_data, MEM_alu_result);
        
        // Test 2@(posedge clk); #1;
        @(posedge clk); #1;
        $display("Test 2: No input(should be same)");
        $display("|     PC+4     | MEMread | MEMwrite | RF_WD select |  opcode  | funct3 |");
        $display("|   %h   |    %b    |     %b    |      %b     |  %b  |  %b  |", MEM_pc_plus_4, MEM_memory_read, MEM_memory_write, MEM_register_file_write_data_select, MEM_opcode, MEM_funct3);
        $display("| Register RD2 |    imm    | csr_read_data |   ALU result   |");
        $display("|   %h   |  %h |   %h    |    %h    |\n", MEM_read_data2, MEM_imm, MEM_csr_read_data, MEM_alu_result);

        // Test 3
        @(negedge clk); 
        EX_pc_plus_4               = 32'h0000_0010;
        EX_memory_read             = 1'b1;            // Load
        EX_memory_write            = 1'b0;
        EX_register_file_write_data_select = 3'b001;  // D_RD -> Register File
        EX_opcode                  = 7'b0000011;      // LOAD opcode
        EX_funct3                  = 3'b010;          // LW
        EX_read_data2              = 32'h0000_0000;   // no RD2
        EX_imm                     = 32'h0000_0018;   // offset 24
        EX_csr_read_data           = 32'h0000_0000;   // no CSR
        EX_alu_result              = 32'h2000_0030;   // Calculation result = x3 + 24
        $display("Test 3-1: new input now(should be same)");
        $display("|     PC+4     | MEMread | MEMwrite | RF_WD select |  opcode  | funct3 |");
        $display("|   %h   |    %b    |     %b    |      %b     |  %b  |  %b  |", MEM_pc_plus_4, MEM_memory_read, MEM_memory_write, MEM_register_file_write_data_select, MEM_opcode, MEM_funct3);
        $display("| Register RD2 |    imm    | csr_read_data |   ALU result   |");
        $display("|   %h   |  %h |   %h    |    %h    |\n", MEM_read_data2, MEM_imm, MEM_csr_read_data, MEM_alu_result);

        @(posedge clk); #1;
        $display("Test 3-2: Test 3-1 input should be output now \n");
        $display("|     PC+4     | MEMread | MEMwrite | RF_WD select |  opcode  | funct3 |");
        $display("|   %h   |    %b    |     %b    |      %b     |  %b  |  %b  |", MEM_pc_plus_4, MEM_memory_read, MEM_memory_write, MEM_register_file_write_data_select, MEM_opcode, MEM_funct3);
        $display("| Register RD2 |    imm    | csr_read_data |   ALU result   |");
        $display("|   %h   |  %h |   %h    |    %h    |\n", MEM_read_data2, MEM_imm, MEM_csr_read_data, MEM_alu_result);

        flush = 1'b1; #10;
        flush = 1'b0;

        // Test 3
        $display("Test 4: Flushed (should be NOP and zero)");
        $display("|     PC+4     | MEMread | MEMwrite | RF_WD select |  opcode  | funct3 |");
        $display("|   %h   |    %b    |     %b    |      %b     |  %b  |  %b  |", MEM_pc_plus_4, MEM_memory_read, MEM_memory_write, MEM_register_file_write_data_select, MEM_opcode, MEM_funct3);
        $display("| Register RD2 |    imm    | csr_read_data |   ALU result   |");
        $display("|   %h   |  %h |   %h    |    %h    |\n", MEM_read_data2, MEM_imm, MEM_csr_read_data, MEM_alu_result);

        EX_pc_plus_4               = 32'h0000_0018;   // (PC+4)
        EX_memory_read             = 1'b0;            // no MEM
        EX_memory_write            = 1'b0;
        EX_register_file_write_data_select = 3'b000;  // ALU result → Register File
        EX_opcode                  = 7'b0110011;      // R-type
        EX_funct3                  = 3'b000;          // ADD
        EX_read_data2              = 32'h0000_0006;   // (dont-care)
        EX_imm                     = 32'h0000_0000;
        EX_csr_read_data           = 32'h1234_5678;   // dummy CSR test value for pipeline
        EX_alu_result              = 32'h0000_000B;   // 0x5 + 0x6 = 11
        $display("Test 5-1: Input begin (should be same)");
        $display("|     PC+4     | MEMread | MEMwrite | RF_WD select |  opcode  | funct3 |");
        $display("|   %h   |    %b    |     %b    |      %b     |  %b  |  %b  |", MEM_pc_plus_4, MEM_memory_read, MEM_memory_write, MEM_register_file_write_data_select, MEM_opcode, MEM_funct3);
        $display("| Register RD2 |    imm    | csr_read_data |   ALU result   |");
        $display("|   %h   |  %h |   %h    |    %h    |\n", MEM_read_data2, MEM_imm, MEM_csr_read_data, MEM_alu_result);
        #10;
        $display("Test 5-2: Test 5-1's input should be output now");
        $display("|     PC+4     | MEMread | MEMwrite | RF_WD select |  opcode  | funct3 |");
        $display("|   %h   |    %b    |     %b    |      %b     |  %b  |  %b  |", MEM_pc_plus_4, MEM_memory_read, MEM_memory_write, MEM_register_file_write_data_select, MEM_opcode, MEM_funct3);
        $display("| Register RD2 |    imm    | csr_read_data |   ALU result   |");
        $display("|   %h   |  %h |   %h    |    %h    |\n", MEM_read_data2, MEM_imm, MEM_csr_read_data, MEM_alu_result);

        $display("\n====================  EX_MEM Register Test END  ====================");

        $stop;
    end

endmodule

RV32I/testbenches/results/waveforms/EX_MEM_Register_tb_result.vcd
$date
	Fri May 23 19:32:51 2025
$end
$version
	Icarus Verilog
$end
$timescale
	1ps
$end
$scope module EX_MEM_Register_tb $end
$scope module ex_mem_register $end
$var wire 32 ! EX_alu_result [31:0] $end
$var wire 32 " EX_csr_read_data [31:0] $end
$var wire 3 # EX_funct3 [2:0] $end
$var wire 32 $ EX_imm [31:0] $end
$var wire 1 % EX_memory_read $end
$var wire 1 & EX_memory_write $end
$var wire 7 ' EX_opcode [6:0] $end
$var wire 32 ( EX_pc_plus_4 [31:0] $end
$var wire 32 ) EX_read_data2 [31:0] $end
$var wire 3 * EX_register_file_write_data_select [2:0] $end
$var wire 1 + clk $end
$var wire 1 , flush $end
$var wire 1 - reset $end
$var parameter 32 . XLEN $end
$var reg 32 / MEM_alu_result [31:0] $end
$var reg 32 0 MEM_csr_read_data [31:0] $end
$var reg 3 1 MEM_funct3 [2:0] $end
$var reg 32 2 MEM_imm [31:0] $end
$var reg 1 3 MEM_memory_read $end
$var reg 1 4 MEM_memory_write $end
$var reg 7 5 MEM_opcode [6:0] $end
$var reg 32 6 MEM_pc_plus_4 [31:0] $end
$var reg 32 7 MEM_read_data2 [31:0] $end
$var reg 3 8 MEM_register_file_write_data_select [2:0] $end
$upscope $end
$upscope $end
$enddefinitions $end
$comment Show the parameter values. $end
$dumpall
b100000 .
$end
#0
$dumpvars
b0 8
b0 7
b0 6
b0 5
04
03
b0 2
b0 1
b0 0
b0 /
1-
0,
0+
bx *
bx )
bx (
bx '
x&
x%
bx $
bx #
bx "
bx !
$end
#5000
1+
#10000
0+
#15000
1+
#20000
0+
#25000
1+
#30000
0+
0-
#35000
bx 0
bx 2
bx 7
bx 1
bx 5
bx 8
x4
x3
bx 6
1+
#40000
0+
#45000
1+
#50000
b10000000000000000000001000000 !
b0 "
b10000 $
b11011110101011011011111011101111 )
b10 #
b100011 '
b0 *
1&
0%
b1000 (
0+
#55000
b0 0
b10000 2
b11011110101011011011111011101111 7
b10 1
b100011 5
b0 8
14
03
b1000 6
1+
#60000
0+
#65000
1+
#70000
b100000000000000000000000110000 !
b11000 $
b0 )
b11 '
b1 *
0&
1%
b10000 (
0+
#75000
b11000 2
b0 7
b11 5
b1 8
04
13
b10000 6
1+
#76000
1,
#80000
0+
#85000
b0 2
b0 1
b0 5
b0 8
03
b0 6
1+
#86000
b1011 !
b10010001101000101011001111000 "
b0 $
b110 )
b0 #
b110011 '
b0 *
0%
b11000 (
0,
#90000
0+
#95000
b10010001101000101011001111000 0
b110 7
b110011 5
b11000 6
1+
