RV32I/modules/Hazard_Unit.v
module HazardUnit (
    input wire clk,
    input wire reset,

    input wire [4:0] ID_rs1,
    input wire [4:0] ID_rs2,
    input wire [4:0] ID_rd,

    input wire branch_prediction_miss,
    input wire EX_jump,

    output reg [1:0] hazard_op,
    output reg IF_ID_flush
);
    reg [1:0] hazard_flag;
    reg [4:0] previous_rd;

    always @(posedge clk or posedge reset) begin
        if (reset) begin
            previous_rd <= 5'b0;
            hazard_op <= 2'b0;
            IF_ID_flush <= 1'b0;
        end else begin
            previous_rd <= ID_rd;
        end
    end

    always @(*) begin
        hazard_op = hazard_flag;
        if (previous_rd != 5'b0) begin
            if (previous_rd == ID_rs1) hazard_flag[0] = 1'b1;
            else hazard_flag[0] = 1'b0;
            if (previous_rd == ID_rs2) hazard_flag[1] = 1'b1;
            else hazard_flag[1] = 1'b0;
        end else hazard_flag = 2'b0;

        if (EX_jump || branch_prediction_miss) begin
            IF_ID_flush <= 1'b1;
        end
    end


    
endmodule

RV32I/testbenches/Hazard_Unit_tb.v
`timescale 1ns/1ps

module HazardUnit_tb;
    reg clk = 0;
    reg reset = 0;
    reg [4:0] ID_rs1;
    reg [4:0] ID_rs2;
    reg [4:0] ID_rd;
    reg branch_prediction_miss; 
    reg EX_jump;

    wire [1:0] hazard_op;
    wire IF_ID_flush;

    HazardUnit hazard_unit (
        .clk(clk),
        .reset(reset),
        .ID_rs1(ID_rs1),
        .ID_rs2(ID_rs2),
        .ID_rd(ID_rd),
        .branch_prediction_miss(branch_prediction_miss),
        .EX_jump(EX_jump),

        .hazard_op(hazard_op),
        .IF_ID_flush(IF_ID_flush)
    );

    always #5 clk = ~clk;

    initial begin
        $dumpfile("testbenches/results/waveforms/Hazard_Unit_tb_result.vcd");
        $dumpvars(0, HazardUnit_tb.hazard_unit);

        $display("==================== Hazard Unit Test START ====================\n");

        // reset signals
        reset = 1'b1;
        branch_prediction_miss = 0;
        EX_jump = 0;
        ID_rs1 = 0;
        ID_rs2 = 0;
        ID_rd = 0;
        #10;
        
        reset = 1'b0;
        @(posedge clk);

        // Test 1 : No RAW hazard
        ID_rs1 = 5'd1;
        ID_rs2 = 5'd2;
        ID_rd = 5'd3;   // rd = 3 now
        @(posedge clk);
        $display("Test 1 (No hazard)");
        $display("hazard_op = %b", hazard_op);
        $display("IF_ID_flush  = %b\n", IF_ID_flush);
        
        // Test 2 : rs1 hazard (prev rd == rs1)
        ID_rs1 = 5'd3;
        ID_rs2 = 5'd4;
        ID_rd = 5'd5;   // prev rd = 3
        @(posedge clk);
        $display("Test 2 (rs1 hazard) : hazard_op = %b (expect 01)", hazard_op);
        $display("IF_ID_flush  = %b (expect 0)\n", IF_ID_flush);

        // Test 3 : rs2 hazard (prev rd == rs2)
        ID_rs1 = 5'd6;
        ID_rs2 = 5'd5;
        ID_rd = 5'd7;   // prev rd = 5
        @(posedge clk);
        $display("Test 3 (rs2 hazard) : hazard_op = %b (expect 10)", hazard_op);
        $display("IF_ID_flush  = %b (expect 0)\n", IF_ID_flush);

        // Test 4 : no hazard 
        ID_rs1 = 5'd22;
        ID_rs2 = 5'd23;
        ID_rd = 5'd7;   // prev rd = 5
        @(posedge clk);
        $display("Test 4 (no hazard) : hazard_op = %b (expect 00)", hazard_op);
        $display("IF_ID_flush  = %b (expect 0)\n", IF_ID_flush);

        // Test 5 : both rs1/rs2 hazards
        ID_rs1 = 5'd7;
        ID_rs2 = 5'd7;
        ID_rd = 5'd8;   // prev rd = 7
        @(posedge clk);
        $display("Test 5 (both)       : hazard_op = %b (expect 11)", hazard_op);
        $display("IF_ID_flush  = %b (expect 0)\n", IF_ID_flush);

        // Test 6 : Branch‑mispredict flush
        branch_prediction_miss = 1'b1;
        @(posedge clk);
        $display("Test 6 (branch prediction miss): ");
        $display("hazard_op = %b (expect 0)", hazard_op);
        $display("IF_ID_flush  = %b (expect 1)\n", IF_ID_flush);

        branch_prediction_miss = 1'b0;

        // Test 7 : Jump flush
        EX_jump = 1'b1;
        @(posedge clk);
        $display("Test 7 (jump): ");
        $display("hazard_op = %b (expect 0)", hazard_op);
        $display("IF_ID_flush  = %b (expect 1)\n", IF_ID_flush);

        EX_jump = 1'b0;

        $display("==================== Hazard Unit Test END ====================\n");
        $stop;
    end

endmodule

RV32I/testbenches/results/waveforms/Hazard_Unit_tb_result.vcd
$date
	Sun May 25 11:17:10 2025
$end
$version
	Icarus Verilog
$end
$timescale
	1ps
$end
$scope module HazardUnit_tb $end
$scope module hazard_unit $end
$var wire 1 ! EX_jump $end
$var wire 5 " ID_rd [4:0] $end
$var wire 5 # ID_rs1 [4:0] $end
$var wire 5 $ ID_rs2 [4:0] $end
$var wire 1 % branch_prediction_miss $end
$var wire 1 & clk $end
$var wire 1 ' reset $end
$var reg 1 ( IF_ID_flush $end
$var reg 2 ) hazard_flag [1:0] $end
$var reg 2 * hazard_op [1:0] $end
$var reg 5 + previous_rd [4:0] $end
$upscope $end
$upscope $end
$enddefinitions $end
$comment Show the parameter values. $end
$dumpall
$end
#0
$dumpvars
b0 +
b0 *
b0 )
0(
1'
0&
0%
b0 $
b0 #
b0 "
0!
$end
#5000
1&
#10000
0&
0'
#15000
b11 +
b11 "
b10 $
b1 #
1&
#20000
0&
#25000
b1 *
b101 +
b0 )
b101 "
b100 $
b11 #
1&
#30000
0&
#35000
b111 +
b0 )
b10 *
b111 "
b101 $
b110 #
1&
#40000
0&
#45000
b0 *
b10111 $
b10110 #
1&
#50000
0&
#55000
b11 *
b1000 +
b0 )
b1000 "
b111 $
b111 #
1&
#60000
0&
#65000
1(
b0 *
1%
1&
#70000
0&
#75000
1!
0%
1&
