RV32I/modules/ID_EX_Register.v
module ID_EX_Register #(
    parameter XLEN = 32
)(
    // pipeline register control signals
    input wire clk,
    input wire reset,
    input wire flush,

    // signal from IF phase
    // input wire [XLEN-1:0] IF_PC but why? What was this for?

    // signals from IF/ID register
    input wire [XLEN-1:0] ID_pc,
    input wire [XLEN-1:0] ID_pc_plus_4,
    input wire ID_branch_estimation,

    // signals from ID phase
    input wire ID_jump,
    input wire ID_branch,
    input wire [1:0] ID_alu_src_A_select,
    input wire [2:0] ID_alu_src_B_select,
    input wire ID_memory_read,
    input wire ID_memory_write,
    input wire [2:0] ID_register_file_write_data_select,
    input wire [6:0] ID_opcode, 
    input wire [2:0] ID_funct3,
    input wire [6:0] ID_funct7,
    input wire [11:0] ID_raw_imm,
    input wire [XLEN-1:0] ID_read_data1,
    input wire [XLEN-1:0] ID_read_data2,
    input wire [4:0] ID_rs1,
    input wire [XLEN-1:0] ID_imm,
    input wire [XLEN-1:0] ID_csr_read_data,

    // signals to EX/MEM register
    output reg [XLEN-1:0] EX_pc,
    output reg [XLEN-1:0] EX_pc_plus_4,
    output reg EX_branch_estimation,

    output reg EX_jump,
    output reg EX_memory_read,
    output reg EX_memory_write,
    output reg [2:0] EX_register_file_write_data_select,
    output reg EX_branch,
    output reg [1:0] EX_alu_src_A_select,
    output reg [2:0] EX_alu_src_B_select,
    output reg [6:0] EX_opcode,
    output reg [2:0] EX_funct3,
    output reg [6:0] EX_funct7,
    output reg [11:0] EX_raw_imm,
    output reg [XLEN-1:0] EX_read_data1,
    output reg [XLEN-1:0] EX_read_data2,
    output reg [4:0] EX_rs1,
    output reg [XLEN-1:0] EX_imm,
    output reg [XLEN-1:0] EX_csr_read_data
);

always @(posedge clk or posedge reset) begin
    if (reset || flush) begin
        EX_pc <= {XLEN{1'b0}};
        EX_pc_plus_4 <= {XLEN{1'b0}};
        EX_branch_estimation <= 1'b0;

        EX_jump <= 1'b0;
        EX_memory_read <= 1'b0;
        EX_memory_write <= 1'b0;
        EX_register_file_write_data_select <= 3'b0;
        EX_branch <= 1'b0;
        EX_alu_src_A_select <= 2'b0;
        EX_alu_src_B_select <= 3'b0;
        EX_opcode <= 7'b0;
        EX_funct3 <= 3'b0;
        EX_funct7 <= 7'b0;
        EX_raw_imm <= 12'b0;
        EX_read_data1 <= {XLEN{1'b0}};
        EX_read_data2 <= {XLEN{1'b0}};
        EX_rs1 <= 5'b0;
        EX_imm <= {XLEN{1'b0}};
        EX_csr_read_data <= {XLEN{1'b0}};
    end else begin
        EX_pc <= ID_pc;
        EX_pc_plus_4 <= ID_pc_plus_4;
        EX_branch_estimation <= ID_branch_estimation;

        EX_jump <= ID_jump;
        EX_memory_read <= ID_memory_read;
        EX_memory_write <= ID_memory_write;
        EX_register_file_write_data_select <= ID_register_file_write_data_select;
        EX_branch <= ID_branch;
        EX_alu_src_A_select <= ID_alu_src_A_select;
        EX_alu_src_B_select <= ID_alu_src_B_select;
        EX_opcode <= ID_opcode;
        EX_funct3 <= ID_funct3;
        EX_funct7 <= ID_funct7;
        EX_raw_imm <= ID_raw_imm;
        EX_read_data1 <= ID_read_data1;
        EX_read_data2 <= ID_read_data2;
        EX_rs1 <= ID_rs1;
        EX_imm <= ID_imm;
        EX_csr_read_data <= ID_csr_read_data;
    end
end

endmodule

RV32I/testbenches/ID_EX_Register_tb.v
`timescale 1ns/1ps

module ID_EX_Register_tb;
    localparam XLEN = 32;

    reg clk = 0;
    reg reset = 0;
    reg flush = 0;

    reg [XLEN-1:0] ID_pc;
    reg [XLEN-1:0] ID_pc_plus_4;
    reg ID_branch_estimation;

    reg ID_jump;
    reg ID_branch;
    reg [1:0] ID_alu_src_A_select;
    reg [2:0] ID_alu_src_B_select;
    reg ID_memory_read;
    reg ID_memory_write;
    reg [2:0] ID_register_file_write_data_select;
    reg [6:0] ID_opcode; 
    reg [2:0] ID_funct3;
    reg [6:0] ID_funct7;
    reg [11:0] ID_raw_imm;
    reg [XLEN-1:0] ID_read_data1;
    reg [XLEN-1:0] ID_read_data2;
    reg [4:0] ID_rs1;
    reg [XLEN-1:0] ID_imm;
    reg [XLEN-1:0] ID_csr_read_data;

    wire [XLEN-1:0] EX_pc;
    wire [XLEN-1:0] EX_pc_plus_4;
    wire EX_branch_estimation;

    wire EX_jump;
    wire EX_memory_read;
    wire EX_memory_write;
    wire [2:0] EX_register_file_write_data_select;
    wire EX_branch;
    wire [1:0] EX_alu_src_A_select;
    wire [2:0] EX_alu_src_B_select;
    wire [6:0] EX_opcode;
    wire [2:0] EX_funct3;
    wire [6:0] EX_funct7;
    wire [11:0] EX_raw_imm;
    wire [XLEN-1:0] EX_read_data1;
    wire [XLEN-1:0] EX_read_data2;
    wire [4:0] EX_rs1;
    wire [XLEN-1:0] EX_imm;
    wire [XLEN-1:0] EX_csr_read_data;

    ID_EX_Register #(.XLEN(32)) id_ex_register (
        .clk(clk),
		.reset(reset),
        .flush(flush),

        .ID_pc(ID_pc),
        .ID_pc_plus_4(ID_pc_plus_4),
        .ID_branch_estimation(ID_branch_estimation),

        .ID_jump(ID_jump),
        .ID_branch(ID_branch),
        .ID_alu_src_A_select(ID_alu_src_A_select),
        .ID_alu_src_B_select(ID_alu_src_B_select),
        .ID_memory_read(ID_memory_read),
        .ID_memory_write(ID_memory_write),
        .ID_register_file_write_data_select(ID_register_file_write_data_select),
        .ID_opcode(ID_opcode), 
        .ID_funct3(ID_funct3),
        .ID_funct7(ID_funct7),
        .ID_raw_imm(ID_raw_imm),
        .ID_read_data1(ID_read_data1),
        .ID_read_data2(ID_read_data2),
        .ID_rs1(ID_rs1),
        .ID_imm(ID_imm),
        .ID_csr_read_data(ID_csr_read_data),

        .EX_pc(EX_pc),
        .EX_pc_plus_4(EX_pc_plus_4),
        .EX_branch_estimation(EX_branch_estimation),

        .EX_jump(EX_jump),
        .EX_memory_read(EX_memory_read),
        .EX_memory_write(EX_memory_write),
        .EX_register_file_write_data_select(EX_register_file_write_data_select),
        .EX_branch(EX_branch),
        .EX_alu_src_A_select(EX_alu_src_A_select),
        .EX_alu_src_B_select(EX_alu_src_B_select),
        .EX_opcode(EX_opcode),
        .EX_funct3(EX_funct3),
        .EX_funct7(EX_funct7),
        .EX_raw_imm(EX_raw_imm),
        .EX_read_data1(EX_read_data1),
        .EX_read_data2(EX_read_data2),
        .EX_rs1(EX_rs1),
        .EX_imm(EX_imm),
        .EX_csr_read_data(EX_csr_read_data)
    );

    always #5 clk = ~clk;

    initial begin
        $dumpfile("testbenches/results/waveforms/ID_EX_Register_tb_result.vcd");
        $dumpvars(0, ID_EX_Register_tb.id_ex_register);

        // Test sequence
        $display("==================== ID_EX Register Test START ====================\n");

        // reset
        reset = 1'b1;
        #30;
        reset = 1'b0;
        @(posedge clk);
        $display("Input now\n");
        $display("     PC    |     PC+4     |   branch estimation  | jump | branch | ALUsrcA | ALUsrcB |");
        $display("|  %h  |   %h   |  %b  |  %b  |  %b  |  %b  |  %b  |", EX_pc, EX_pc_plus_4, EX_branch_estimation, EX_jump, EX_branch, EX_alu_src_A_select, EX_alu_src_B_select);
        $display("| MEMread | MEMwrite | RF_WD select | opcode | funct3 | funct7 | raw_imm |");
        $display("|  %b  |   %b   |  %b  |  %b  |  %b  |  %b  |  %b  |", EX_memory_read, EX_memory_write, EX_register_file_write_data_select, EX_opcode, EX_funct3, EX_funct7, EX_raw_imm);
        $display("| Register RD1 | Register RD2 | rs1 | imm | csr_read_data |");
        $display("|  %h  |   %h   |  %b  |  %b  |  %h  |\n", EX_read_data1, EX_read_data2, EX_rs1, EX_imm, EX_csr_read_data);
        #10;
        
        // Test 1
        @(negedge clk); 
        ID_pc = 32'h00000000;
        ID_pc_plus_4 = 32'h0000_0004;
        ID_branch_estimation = 1'b0;

        ID_jump = 1'b1;
        ID_branch = 1'b0;
        ID_alu_src_A_select = 2'b01;
        ID_alu_src_B_select = 2'b10;
        ID_memory_read = 1'b0;
        ID_memory_write = 1'b0;
        ID_register_file_write_data_select = 3'b001;
        ID_opcode = 7'b0011000;
        ID_funct3 = 3'b010;
        ID_funct7 = 7'b0011110;
        ID_raw_imm = 12'b0;
        ID_read_data1 = 32'hAAAA_AAAA;
        ID_read_data2 = 32'hBBBB_BBBB;
        ID_rs1 = 5'b01100;
        ID_imm = 32'h0000_0000;
        ID_csr_read_data = 32'h0000_0000;

        @(posedge clk); #1;
        $display("Test 1: Previous value should be output now\n");
        $display("     PC    |     PC+4     |   branch estimation  | jump | branch | ALUsrcA | ALUsrcB |");
        $display("|  %h  |   %h   |  %b  |  %b  |  %b  |  %b  |  %b  |", EX_pc, EX_pc_plus_4, EX_branch_estimation, EX_jump, EX_branch, EX_alu_src_A_select, EX_alu_src_B_select);
        $display("| MEMread | MEMwrite | RF_WD select | opcode | funct3 | funct7 | raw_imm |");
        $display("|  %b  |   %b   |  %b  |  %b  |  %b  |  %b  |  %b  |", EX_memory_read, EX_memory_write, EX_register_file_write_data_select, EX_opcode, EX_funct3, EX_funct7, EX_raw_imm);
        $display("| Register RD1 | Register RD2 | rs1 | imm | csr_read_data |");
        $display("|  %h  |   %h   |  %b  |  %b  |  %h  |\n", EX_read_data1, EX_read_data2, EX_rs1, EX_imm, EX_csr_read_data);
        
        // Test 2@(posedge clk); #1;
        @(posedge clk); #1;
        $display("Test 2: No input(should be same)\n");
        $display("     PC    |     PC+4     |   branch estimation  | jump | branch | ALUsrcA | ALUsrcB |");
        $display("|  %h  |   %h   |  %b  |  %b  |  %b  |  %b  |  %b  |", EX_pc, EX_pc_plus_4, EX_branch_estimation, EX_jump, EX_branch, EX_alu_src_A_select, EX_alu_src_B_select);
        $display("| MEMread | MEMwrite | RF_WD select | opcode | funct3 | funct7 | raw_imm |");
        $display("|  %b  |   %b   |  %b  |  %b  |  %b  |  %b  |  %b  |", EX_memory_read, EX_memory_write, EX_register_file_write_data_select, EX_opcode, EX_funct3, EX_funct7, EX_raw_imm);
        $display("| Register RD1 | Register RD2 | rs1 | imm | csr_read_data |");
        $display("|  %h  |   %h   |  %b  |  %b  |  %h  |\n", EX_read_data1, EX_read_data2, EX_rs1, EX_imm, EX_csr_read_data);

        // Test 3
        @(negedge clk); 
        ID_pc                         = 32'h0000_0000;
        ID_pc_plus_4                  = 32'h0000_0004;
        ID_branch_estimation          = 1'b0;

        ID_jump                       = 1'b0;
        ID_branch                     = 1'b0;
        ID_alu_src_A_select           = 2'b00;      // rs1
        ID_alu_src_B_select           = 3'b000;     // rs2
        ID_memory_read                = 1'b0;
        ID_memory_write               = 1'b0;
        ID_register_file_write_data_select = 3'b000; // ALU result
        ID_opcode                     = 7'b0110011; // R-type
        ID_funct3                     = 3'b000;     // ADD
        ID_funct7                     = 7'b0000000; 
        ID_raw_imm                    = 12'h000;
        ID_read_data1                 = 32'h0000_0005; 
        ID_read_data2                 = 32'h0000_000A;
        ID_rs1                        = 5'd5;
        ID_imm                        = 32'h0000_0000;
        ID_csr_read_data              = 32'h0000_0000;
        $display("Test 3-1: new input now(should be same) \n");
        $display("     PC    |     PC+4     |   branch estimation  | jump | branch | ALUsrcA | ALUsrcB |");
        $display("|  %h  |   %h   |  %b  |  %b  |  %b  |  %b  |  %b  |", EX_pc, EX_pc_plus_4, EX_branch_estimation, EX_jump, EX_branch, EX_alu_src_A_select, EX_alu_src_B_select);
        $display("| MEMread | MEMwrite | RF_WD select | opcode | funct3 | funct7 | raw_imm |");
        $display("|  %b  |   %b   |  %b  |  %b  |  %b  |  %b  |  %b  |", EX_memory_read, EX_memory_write, EX_register_file_write_data_select, EX_opcode, EX_funct3, EX_funct7, EX_raw_imm);
        $display("| Register RD1 | Register RD2 | rs1 | imm | csr_read_data |");
        $display("|  %h  |   %h   |  %b  |  %b  |  %h  |\n", EX_read_data1, EX_read_data2, EX_rs1, EX_imm, EX_csr_read_data);

        @(posedge clk); #1;
        $display("Test 3-2: Test 3-1 input should be output now \n");
        $display("     PC    |     PC+4     |   branch estimation  | jump | branch | ALUsrcA | ALUsrcB |");
        $display("|  %h  |   %h   |  %b  |  %b  |  %b  |  %b  |  %b  |", EX_pc, EX_pc_plus_4, EX_branch_estimation, EX_jump, EX_branch, EX_alu_src_A_select, EX_alu_src_B_select);
        $display("| MEMread | MEMwrite | RF_WD select | opcode | funct3 | funct7 | raw_imm |");
        $display("|  %b  |   %b   |  %b  |  %b  |  %b  |  %b  |  %b  |", EX_memory_read, EX_memory_write, EX_register_file_write_data_select, EX_opcode, EX_funct3, EX_funct7, EX_raw_imm);
        $display("| Register RD1 | Register RD2 | rs1 | imm | csr_read_data |");
        $display("|  %h  |   %h   |  %b  |  %b  |  %h  |\n", EX_read_data1, EX_read_data2, EX_rs1, EX_imm, EX_csr_read_data);

        flush = 1'b1; #10;
        flush = 1'b0;

        // Test 3
        $display("Test 4: Flushed (should be NOP and zero)\n");
        $display("     PC    |     PC+4     |   branch estimation  | jump | branch | ALUsrcA | ALUsrcB |");
        $display("|  %h  |   %h   |  %b  |  %b  |  %b  |  %b  |  %b  |", EX_pc, EX_pc_plus_4, EX_branch_estimation, EX_jump, EX_branch, EX_alu_src_A_select, EX_alu_src_B_select);
        $display("| MEMread | MEMwrite | RF_WD select | opcode | funct3 | funct7 | raw_imm |");
        $display("|  %b  |   %b   |  %b  |  %b  |  %b  |  %b  |  %b  |", EX_memory_read, EX_memory_write, EX_register_file_write_data_select, EX_opcode, EX_funct3, EX_funct7, EX_raw_imm);
        $display("| Register RD1 | Register RD2 | rs1 | imm | csr_read_data |");
        $display("|  %h  |   %h   |  %b  |  %b  |  %h  |\n", EX_read_data1, EX_read_data2, EX_rs1, EX_imm, EX_csr_read_data);

        ID_pc                         = 32'h1000_1000;
        ID_pc_plus_4                  = 32'h1000_1004;
        ID_branch_estimation          = 1'b1;       // branch predicted taken

        ID_jump                       = 1'b0;
        ID_branch                     = 1'b1;
        ID_alu_src_A_select           = 2'b00;      // rs1 base
        ID_alu_src_B_select           = 3'b001;     // imm
        ID_memory_read                = 1'b1;
        ID_memory_write               = 1'b0;
        ID_register_file_write_data_select = 3'b001; // MEM data
        ID_opcode                     = 7'b0000011; // I-type LOAD
        ID_funct3                     = 3'b010;     // LW
        ID_funct7                     = 7'b0000000;
        ID_raw_imm                    = 12'h0F0;
        ID_read_data1                 = 32'h0000_0004; 
        ID_read_data2                 = 32'h0000_0000; // unused for load
        ID_rs1                        = 5'd2;
        ID_imm                        = 32'h0000_00F0;
        ID_csr_read_data              = 32'h0000_0000;
        $display("Test 5-1: Input begin (should be same)\n");
        $display("     PC    |     PC+4     |   branch estimation  | jump | branch | ALUsrcA | ALUsrcB |");
        $display("|  %h  |   %h   |  %b  |  %b  |  %b  |  %b  |  %b  |", EX_pc, EX_pc_plus_4, EX_branch_estimation, EX_jump, EX_branch, EX_alu_src_A_select, EX_alu_src_B_select);
        $display("| MEMread | MEMwrite | RF_WD select | opcode | funct3 | funct7 | raw_imm |");
        $display("|  %b  |   %b   |  %b  |  %b  |  %b  |  %b  |  %b  |", EX_memory_read, EX_memory_write, EX_register_file_write_data_select, EX_opcode, EX_funct3, EX_funct7, EX_raw_imm);
        $display("| Register RD1 | Register RD2 | rs1 | imm | csr_read_data |");
        $display("|  %h  |   %h   |  %b  |  %b  |  %h  |\n", EX_read_data1, EX_read_data2, EX_rs1, EX_imm, EX_csr_read_data);
        #10;
        $display("Test 5-2: Test 5-1's input should be output now\n");
        $display("     PC    |     PC+4     |   branch estimation  | jump | branch | ALUsrcA | ALUsrcB |");
        $display("|  %h  |   %h   |  %b  |  %b  |  %b  |  %b  |  %b  |", EX_pc, EX_pc_plus_4, EX_branch_estimation, EX_jump, EX_branch, EX_alu_src_A_select, EX_alu_src_B_select);
        $display("| MEMread | MEMwrite | RF_WD select | opcode | funct3 | funct7 | raw_imm |");
        $display("|  %b  |   %b   |  %b  |  %b  |  %b  |  %b  |  %b  |", EX_memory_read, EX_memory_write, EX_register_file_write_data_select, EX_opcode, EX_funct3, EX_funct7, EX_raw_imm);
        $display("| Register RD1 | Register RD2 | rs1 | imm | csr_read_data |");
        $display("|  %h  |   %h   |  %b  |  %b  |  %h  |\n", EX_read_data1, EX_read_data2, EX_rs1, EX_imm, EX_csr_read_data);

        $display("\n====================  ID_EX Register Test END  ====================");

        $stop;
    end

endmodule

RV32I/testbenches/results/waveforms/ID_EX_Register_tb_result.vcd
$date
	Thu May 22 23:58:43 2025
$end
$version
	Icarus Verilog
$end
$timescale
	1ps
$end
$scope module ID_EX_Register_tb $end
$scope module id_ex_register $end
$var wire 2 ! ID_alu_src_A_select [1:0] $end
$var wire 3 " ID_alu_src_B_select [2:0] $end
$var wire 1 # ID_branch $end
$var wire 1 $ ID_branch_estimation $end
$var wire 32 % ID_csr_read_data [31:0] $end
$var wire 3 & ID_funct3 [2:0] $end
$var wire 7 ' ID_funct7 [6:0] $end
$var wire 32 ( ID_imm [31:0] $end
$var wire 1 ) ID_jump $end
$var wire 1 * ID_memory_read $end
$var wire 1 + ID_memory_write $end
$var wire 7 , ID_opcode [6:0] $end
$var wire 32 - ID_pc [31:0] $end
$var wire 32 . ID_pc_plus_4 [31:0] $end
$var wire 12 / ID_raw_imm [11:0] $end
$var wire 32 0 ID_read_data1 [31:0] $end
$var wire 32 1 ID_read_data2 [31:0] $end
$var wire 3 2 ID_register_file_write_data_select [2:0] $end
$var wire 5 3 ID_rs1 [4:0] $end
$var wire 1 4 clk $end
$var wire 1 5 flush $end
$var wire 1 6 reset $end
$var parameter 32 7 XLEN $end
$var reg 2 8 EX_alu_src_A_select [1:0] $end
$var reg 3 9 EX_alu_src_B_select [2:0] $end
$var reg 1 : EX_branch $end
$var reg 1 ; EX_branch_estimation $end
$var reg 32 < EX_csr_read_data [31:0] $end
$var reg 3 = EX_funct3 [2:0] $end
$var reg 7 > EX_funct7 [6:0] $end
$var reg 32 ? EX_imm [31:0] $end
$var reg 1 @ EX_jump $end
$var reg 1 A EX_memory_read $end
$var reg 1 B EX_memory_write $end
$var reg 7 C EX_opcode [6:0] $end
$var reg 32 D EX_pc [31:0] $end
$var reg 32 E EX_pc_plus_4 [31:0] $end
$var reg 12 F EX_raw_imm [11:0] $end
$var reg 32 G EX_read_data1 [31:0] $end
$var reg 32 H EX_read_data2 [31:0] $end
$var reg 3 I EX_register_file_write_data_select [2:0] $end
$var reg 5 J EX_rs1 [4:0] $end
$upscope $end
$upscope $end
$enddefinitions $end
$comment Show the parameter values. $end
$dumpall
b100000 7
$end
#0
$dumpvars
b0 J
b0 I
b0 H
b0 G
b0 F
b0 E
b0 D
b0 C
0B
0A
0@
b0 ?
b0 >
b0 =
b0 <
0;
0:
b0 9
b0 8
16
05
04
bx 3
bx 2
bx 1
bx 0
bx /
bx .
bx -
bx ,
x+
x*
x)
bx (
bx '
bx &
bx %
x$
x#
bx "
bx !
$end
#5000
14
#10000
04
#15000
14
#20000
04
#25000
14
#30000
04
06
#35000
bx <
bx ?
bx J
bx H
bx G
bx F
bx >
bx =
bx C
bx 9
bx 8
x:
bx I
xB
xA
x@
x;
bx E
bx D
14
#40000
04
#45000
14
#50000
b0 %
b0 (
b1100 3
b10111011101110111011101110111011 1
b10101010101010101010101010101010 0
b0 /
b11110 '
b10 &
b11000 ,
b1 2
0+
0*
b10 "
b1 !
0#
1)
0$
b100 .
b0 -
04
#55000
b0 <
b0 ?
b1100 J
b10111011101110111011101110111011 H
b10101010101010101010101010101010 G
b0 F
b11110 >
b10 =
b11000 C
b10 9
b1 8
0:
b1 I
0B
0A
1@
0;
b100 E
b0 D
14
#60000
04
#65000
14
#70000
b101 3
b1010 1
b101 0
b0 '
b0 &
b110011 ,
b0 2
b0 "
b0 !
0)
04
#75000
b101 J
b1010 H
b101 G
b0 >
b0 =
b110011 C
b0 9
b0 8
b0 I
0@
14
#76000
15
#80000
04
#85000
b0 J
b0 H
b0 G
b0 C
b0 E
14
#86000
b11110000 (
b10 3
b0 1
b100 0
b11110000 /
b10 &
b11 ,
b1 2
1*
b1 "
1#
1$
b10000000000000001000000000100 .
b10000000000000001000000000000 -
05
#90000
04
#95000
b11110000 ?
b10 J
b100 G
b11110000 F
b10 =
b11 C
b1 9
1:
b1 I
1A
1;
b10000000000000001000000000100 E
b10000000000000001000000000000 D
14
