RV32I/modules/IF_ID_Register.v
module IF_ID_Register #(
    parameter XLEN = 32
)(
    // pipeline register control signals
    input wire clk,
    input wire reset,
    input wire flush,

    // signals from IF phase
    input wire [XLEN-1:0] IF_pc,
    input wire [XLEN-1:0] IF_pc_plus_4,
    input wire [31:0] IF_instruction,
    input wire IF_branch_estimation,

    // signals to ID/EX register
    output reg [XLEN-1:0] ID_pc,
    output reg [XLEN-1:0] ID_pc_plus_4,
    output reg [31:0] ID_instruction,
    output reg ID_branch_estimation
);

always @(posedge clk or posedge reset) begin
    if (reset) begin
        ID_pc <= {XLEN{1'b0}};
        ID_pc_plus_4 <= {XLEN{1'b0}};
        ID_instruction <= 32'b0;
        ID_branch_estimation <= 1'b0;
    end 
    else if (flush) begin   
        ID_pc <= {XLEN{1'b0}};
        ID_pc_plus_4 <= {XLEN{1'b0}};
        ID_instruction <= 32'h0000_0013; // ADDI x0, x0, 0 = RISC-V NOP, HINT
        ID_branch_estimation <= 1'b0;
    end
    else begin
        ID_pc <= IF_pc;
        ID_pc_plus_4 <= IF_pc_plus_4;
        ID_instruction <= IF_instruction;
        ID_branch_estimation <= IF_branch_estimation;
    end
end

endmodule

RV32I/testbenches/IF_ID_Register_tb.v
`timescale 1ns/1ps

module IF_ID_Register_tb;
    localparam XLEN = 32;

    reg clk = 0;
    reg reset;
    reg flush;

    reg [XLEN-1:0] IF_pc;
    reg [XLEN-1:0] IF_pc_plus_4;
    reg [31:0] IF_instruction;
    reg IF_branch_estimation;

    wire [XLEN-1:0] ID_pc;
    wire [XLEN-1:0] ID_pc_plus_4;
    wire [31:0] ID_instruction;
    wire ID_branch_estimation;

    IF_ID_Register #(.XLEN(32)) if_id_register (
        .clk(clk),
		.reset(reset),
        .flush(flush),

        .IF_pc(IF_pc),
        .IF_pc_plus_4(IF_pc_plus_4),
        .IF_instruction(IF_instruction),
        .IF_branch_estimation(IF_branch_estimation),

        .ID_pc(ID_pc),
        .ID_pc_plus_4(ID_pc_plus_4),
        .ID_instruction(ID_instruction),
        .ID_branch_estimation(ID_branch_estimation)
    );

    always #5 clk = ~clk;

    initial begin
        $dumpfile("testbenches/results/waveforms/IF_ID_Register_tb_result.vcd");
        $dumpvars(0, IF_ID_Register_tb.if_id_register);

        // Test sequence
        $display("==================== IF_ID Register Test START ====================\n");

        // reset
        reset = 1'b1;
        #30;
        reset = 1'b0;
        @(posedge clk);
        $display("Input now\n Initial PC |     PC+4     |   instruction  | branch estimation |\n %h  |   %h   |    %h    |      %h      |\n", ID_pc, ID_pc_plus_4, ID_instruction, ID_branch_estimation);
        #10;
        
        // Test 1
        @(negedge clk); 
        IF_pc = 32'h00000000;
        IF_pc_plus_4 = 32'h0000_0004;
        IF_instruction = 32'h2bc0_0093; // ADDI:  x1 = x0 + 2BC
        IF_branch_estimation = 1'b0;
        @(posedge clk); #1;
        $display("Test 1: Previous value should be output now\n     PC    |     PC+4     |   instruction  | branch estimation |\n %h  |   %h   |    %h    |      %h      |\n", ID_pc, ID_pc_plus_4, ID_instruction, ID_branch_estimation);
        
        // Test 2@(posedge clk); #1;
        @(posedge clk); #1;
        $display("Test 2: No input(should be same)\n     PC    |     PC+4     |   instruction  | branch estimation |\n %h  |   %h   |    %h    |      %h      |\n", ID_pc, ID_pc_plus_4, ID_instruction, ID_branch_estimation);

        // Test 3
        @(negedge clk); 
        IF_pc = 32'h1111_1110;
        IF_pc_plus_4 = 32'h1111_1114;
        IF_instruction = 32'h2bc0_0093; // ADDI:  x1 = x0 + 2BC
        IF_branch_estimation = 1'b1; #1
        $display("Test 3-1: new input now(should be same) \n     PC    |     PC+4     |   instruction  | branch estimation |\n %h  |   %h   |    %h    |      %h      |\n", ID_pc, ID_pc_plus_4, ID_instruction, ID_branch_estimation);

        @(posedge clk); #1;
        $display("Test 3-2: Test 3-1 input should be output now \n     PC    |     PC+4     |   instruction  | branch estimation |\n %h  |   %h   |    %h    |      %h      |\n", ID_pc, ID_pc_plus_4, ID_instruction, ID_branch_estimation);

        flush = 1'b1; #10;
        flush = 1'b0;

        // Test 3
        $display("Test 4: Flushed (should be NOP and zero)\n     PC    |     PC+4     |   instruction  | branch estimation |\n %h  |   %h   |    %h    |      %h      |\n", ID_pc, ID_pc_plus_4, ID_instruction, ID_branch_estimation);
        IF_pc = 32'h1111_1110;
        IF_pc_plus_4 = 32'h1111_1114;
        IF_instruction = 32'h2bc0_0093; // ADDI:  x1 = x0 + 2BC
        IF_branch_estimation = 1'b1;
        $display("Test 5-1: Input begin (should be same)\n     PC    |     PC+4     |   instruction  | branch estimation |\n %h  |   %h   |    %h    |      %h      |\n", ID_pc, ID_pc_plus_4, ID_instruction, ID_branch_estimation);
        #10;
        $display("Test 5-2: Test 5-1's input should be output now\n     PC    |     PC+4     |   instruction  | branch estimation |\n %h  |   %h   |    %h    |      %h      |\n", ID_pc, ID_pc_plus_4, ID_instruction, ID_branch_estimation);

        $display("\n====================  IF_ID Register Test END  ====================");

        $stop;
    end

endmodule

RV32I/testbenches/results/waveforms/IF_ID_Register_tb_result.vcd
$date
	Thu May 22 22:57:04 2025
$end
$version
	Icarus Verilog
$end
$timescale
	1ps
$end
$scope module IF_ID_Register_tb $end
$scope module if_id_register $end
$var wire 1 ! IF_branch_estimation $end
$var wire 32 " IF_instruction [31:0] $end
$var wire 32 # IF_pc [31:0] $end
$var wire 32 $ IF_pc_plus_4 [31:0] $end
$var wire 1 % clk $end
$var wire 1 & flush $end
$var wire 1 ' reset $end
$var parameter 32 ( XLEN $end
$var reg 1 ) ID_branch_estimation $end
$var reg 32 * ID_instruction [31:0] $end
$var reg 32 + ID_pc [31:0] $end
$var reg 32 , ID_pc_plus_4 [31:0] $end
$upscope $end
$upscope $end
$enddefinitions $end
$comment Show the parameter values. $end
$dumpall
b100000 (
$end
#0
$dumpvars
b0 ,
b0 +
b0 *
0)
1'
0&
0%
bx $
bx #
bx "
x!
$end
#5000
1%
#10000
0%
#15000
1%
#20000
0%
#25000
1%
#30000
0%
0'
#35000
x)
bx *
bx ,
bx +
1%
#40000
0%
#45000
1%
#50000
0!
b101011110000000000000010010011 "
b100 $
b0 #
0%
#55000
0)
b101011110000000000000010010011 *
b100 ,
b0 +
1%
#60000
0%
#65000
1%
#70000
1!
b10001000100010001000100010100 $
b10001000100010001000100010000 #
0%
#75000
1)
b10001000100010001000100010100 ,
b10001000100010001000100010000 +
1%
#76000
1&
#80000
0%
#85000
0)
b10011 *
b0 ,
b0 +
1%
#86000
0&
#90000
0%
#95000
1)
b101011110000000000000010010011 *
b10001000100010001000100010100 ,
b10001000100010001000100010000 +
1%
