RV32I/modules/MEM_WB_Register.v
module MEM_WB_Register #(
    parameter XLEN = 32
)(
    // pipeline register control signals
    input wire clk,
    input wire reset,
    input wire flush,

    // signals from EX/MEM register
    input wire [XLEN-1:0] MEM_pc_plus_4,

    input wire [2:0] MEM_register_file_write_data_select,
    input wire [XLEN-1:0] MEM_imm,
    input wire [XLEN-1:0] MEM_csr_read_data,
    input wire [XLEN-1:0] MEM_alu_result,
    input wire MEM_register_write_enable,
    input wire MEM_csr_write_enable,
    input wire [4:0] MEM_rd,

    // signals from MEM phase
    input wire [XLEN-1:0] MEM_register_file_write_data,

    // signals to MEM register
    output reg [XLEN-1:0] WB_pc_plus_4,

    output reg [2:0] WB_register_file_write_data_select,
    output reg [XLEN-1:0] WB_imm,
    output reg [XLEN-1:0] WB_csr_read_data,
    output reg [XLEN-1:0] WB_alu_result,
    output reg WB_register_write_enable,
    output reg WB_csr_write_enable,
    output reg [4:0] WB_rd,

    output reg [XLEN-1:0] WB_register_file_write_data
);

always @(posedge clk or posedge reset) begin
    if (reset || flush) begin
        WB_pc_plus_4 <= {XLEN{1'b0}};

        WB_register_file_write_data_select <= 3'b0;
        WB_imm <= {XLEN{1'b0}};
        WB_csr_read_data <= {XLEN{1'b0}};
        WB_alu_result <= {XLEN{1'b0}};
        WB_register_write_enable <= 1'b0;
        WB_csr_write_enable <= 1'b0;
        WB_rd <= 5'b0;
        
        WB_register_file_write_data <= {XLEN{1'b0}};
    end else begin
        WB_pc_plus_4 <= MEM_pc_plus_4;

        WB_register_file_write_data_select <= MEM_register_file_write_data_select;
        WB_imm <= MEM_imm;
        WB_csr_read_data <= MEM_csr_read_data;
        WB_alu_result <= MEM_alu_result;
        WB_register_write_enable <= MEM_register_write_enable;
        WB_csr_write_enable <= MEM_csr_write_enable;
        WB_rd <= MEM_rd;
        
        WB_register_file_write_data <= MEM_register_file_write_data;
    end
end

endmodule

RV32I/testbenches/MEM_WB_Register_tb.v
`timescale 1ns/1ps

module MEM_WB_Register_tb;
    localparam XLEN = 32;

    reg clk = 0;
    reg reset = 0;
    reg flush = 0;

    reg [XLEN-1:0] MEM_pc_plus_4;

    // signals from 
    reg [2:0] MEM_register_file_write_data_select;
    reg [XLEN-1:0] MEM_imm;
    reg [XLEN-1:0] MEM_csr_read_data;
    reg [XLEN-1:0] MEM_alu_result;
    reg MEM_register_write_enable;
    reg MEM_csr_write_enable;

    // signals from MEM phase
    reg [XLEN-1:0] MEM_register_file_write_data;

    wire [XLEN-1:0] WB_pc_plus_4;

    wire [2:0] WB_register_file_write_data_select;
    wire [XLEN-1:0] WB_imm;
    wire [XLEN-1:0] WB_csr_read_data;
    wire [XLEN-1:0] WB_alu_result;
    wire WB_register_write_enable;
    wire WB_csr_write_enable;

    wire [XLEN-1:0] WB_register_file_write_data;

    MEM_WB_Register #(.XLEN(32)) mem_wb_register (
        .clk(clk),
		.reset(reset),
        .flush(flush),

        .MEM_pc_plus_4(MEM_pc_plus_4),
        .MEM_register_file_write_data_select(MEM_register_file_write_data_select),
        .MEM_imm(MEM_imm),
        .MEM_csr_read_data(MEM_csr_read_data),
        .MEM_alu_result(MEM_alu_result),
        .MEM_register_write_enable(MEM_register_write_enable),
        .MEM_csr_write_enable(MEM_csr_write_enable),
        .MEM_register_file_write_data,

        .WB_pc_plus_4(WB_pc_plus_4),
        .WB_register_file_write_data_select(WB_register_file_write_data_select),
        .WB_imm(WB_imm),
        .WB_csr_read_data(WB_csr_read_data),
        .WB_alu_result(WB_alu_result),
        .WB_register_write_enable(WB_register_write_enable),
        .WB_csr_write_enable(WB_csr_write_enable),
        .WB_register_file_write_data(WB_register_file_write_data)
    );

    always #5 clk = ~clk;

    initial begin
        $dumpfile("testbenches/results/waveforms/MEM_WB_Register_tb_result.vcd");
        $dumpvars(0, MEM_WB_Register_tb.mem_wb_register);

        // Test sequence
        $display("==================== MEM_WB_Register Test START ====================\n");

        // reset
        reset = 1'b1;
        #30;
        reset = 1'b0;
        @(posedge clk);
        $display("Input now");
        $display("|     PC+4     | RF_WD select |  CSR Write Enable | RegF Write Enable |");
        $display("|   %h   |      %b     |         %b         |         %b         |", WB_pc_plus_4, WB_register_file_write_data_select, WB_csr_write_enable, WB_register_write_enable);
        $display("|    BERF_WD   |     imm    | csr_read_data |   ALU result   |");
        $display("|   %h   |  %h  |   %h    |    %h    |\n", WB_register_file_write_data, WB_imm, WB_csr_read_data, WB_alu_result);
        #10;
        
        // Test 1
        @(negedge clk); 
        MEM_pc_plus_4                    = 32'h0000_0004;
        MEM_register_file_write_data_select = 3'b010;       // ALU result -> Register File
        MEM_imm                          = 32'h0000_0000;
        MEM_csr_read_data                = 32'h0000_0000;
        MEM_alu_result                   = 32'h0000_000B;   // ALU result = 11
        MEM_register_write_enable        = 1'b1;            // Register Write Enable
        MEM_csr_write_enable             = 1'b0;
        MEM_register_file_write_data     = 32'h0000_000A;   // Dummy BERF_WD data value

        @(posedge clk); #1;
        $display("Test 1: Previous value should be output now");
        $display("|     PC+4     | RF_WD select |  CSR Write Enable | RegF Write Enable |");
        $display("|   %h   |      %b     |         %b         |         %b         |", WB_pc_plus_4, WB_register_file_write_data_select, WB_csr_write_enable, WB_register_write_enable);
        $display("|    BERF_WD   |     imm    | csr_read_data |   ALU result   |");
        $display("|   %h   |  %h  |   %h    |    %h    |\n", WB_register_file_write_data, WB_imm, WB_csr_read_data, WB_alu_result);
        
        // Test 2@(posedge clk); #1;
        @(posedge clk); #1;
        $display("Test 2: No input(should be same)");
        $display("|     PC+4     | RF_WD select |  CSR Write Enable | RegF Write Enable |");
        $display("|   %h   |      %b     |         %b         |         %b         |", WB_pc_plus_4, WB_register_file_write_data_select, WB_csr_write_enable, WB_register_write_enable);
        $display("|    BERF_WD   |     imm    | csr_read_data |   ALU result   |");
        $display("|   %h   |  %h  |   %h    |    %h    |\n", WB_register_file_write_data, WB_imm, WB_csr_read_data, WB_alu_result);

        // Test 3
        @(negedge clk); 
        MEM_pc_plus_4                    = 32'h0000_0008;
        MEM_register_file_write_data_select = 3'b001;       // D_RD → Register File
        MEM_imm                          = 32'h0000_0020;   // offset 32
        MEM_csr_read_data                = 32'h0000_0000;
        MEM_alu_result                   = 32'h1000_0020;   // ALU result = x3 + 32
        MEM_register_write_enable        = 1'b1;
        MEM_csr_write_enable             = 1'b0;
        MEM_register_file_write_data     = 32'hDEAD_BEEF;   // Dummy BERF_WD data value
        $display("Test 3-1: new input now(should be same)");
        $display("|     PC+4     | RF_WD select |  CSR Write Enable | RegF Write Enable |");
        $display("|   %h   |      %b     |         %b         |         %b         |", WB_pc_plus_4, WB_register_file_write_data_select, WB_csr_write_enable, WB_register_write_enable);
        $display("|    BERF_WD   |     imm    | csr_read_data |   ALU result   |");
        $display("|   %h   |  %h  |   %h    |    %h    |\n", WB_register_file_write_data, WB_imm, WB_csr_read_data, WB_alu_result);

        @(posedge clk); #1;
        $display("Test 3-2: Test 3-1 input should be output now \n");
        $display("|     PC+4     | RF_WD select |  CSR Write Enable | RegF Write Enable |");
        $display("|   %h   |      %b     |         %b         |         %b         |", WB_pc_plus_4, WB_register_file_write_data_select, WB_csr_write_enable, WB_register_write_enable);
        $display("|    BERF_WD   |     imm    | csr_read_data |   ALU result   |");
        $display("|   %h   |  %h  |   %h    |    %h    |\n", WB_register_file_write_data, WB_imm, WB_csr_read_data, WB_alu_result);

        flush = 1'b1; #10;
        flush = 1'b0;

        // Test 3
        $display("Test 4: Flushed (should be NOP and zero)");
        $display("|     PC+4     | RF_WD select |  CSR Write Enable | RegF Write Enable |");
        $display("|   %h   |      %b     |         %b         |         %b         |", WB_pc_plus_4, WB_register_file_write_data_select, WB_csr_write_enable, WB_register_write_enable);
        $display("|    BERF_WD   |     imm    | csr_read_data |   ALU result   |");
        $display("|   %h   |  %h  |   %h    |    %h    |\n", WB_register_file_write_data, WB_imm, WB_csr_read_data, WB_alu_result);

        MEM_pc_plus_4                    = 32'h0000_000C;
        MEM_register_file_write_data_select = 3'b011;       // CSR read → Register File
        MEM_imm                          = 32'h0000_0000;
        MEM_csr_read_data                = 32'hCAFE_BABE;   // CSR value
        MEM_alu_result                   = 32'h0000_0000;   // no ALU
        MEM_register_write_enable        = 1'b1;            // rd ← CSR
        MEM_csr_write_enable             = 1'b1;            // CSR write enable
        MEM_register_file_write_data     = 32'hCAFE_BABE;   // Dummy BERF_WD data value
        $display("Test 5-1: Input begin (should be same)");
        $display("|     PC+4     | RF_WD select |  CSR Write Enable | RegF Write Enable |");
        $display("|   %h   |      %b     |         %b         |         %b         |", WB_pc_plus_4, WB_register_file_write_data_select, WB_csr_write_enable, WB_register_write_enable);
        $display("|    BERF_WD   |     imm    | csr_read_data |   ALU result   |");
        $display("|   %h   |  %h  |   %h    |    %h    |\n", WB_register_file_write_data, WB_imm, WB_csr_read_data, WB_alu_result);
        #10;
        $display("Test 5-2: Test 5-1's input should be output now");
        $display("|     PC+4     | RF_WD select |  CSR Write Enable | RegF Write Enable |");
        $display("|   %h   |      %b     |         %b         |         %b         |", WB_pc_plus_4, WB_register_file_write_data_select, WB_csr_write_enable, WB_register_write_enable);
        $display("|    BERF_WD   |     imm    | csr_read_data |   ALU result   |");
        $display("|   %h   |  %h  |   %h    |    %h    |\n", WB_register_file_write_data, WB_imm, WB_csr_read_data, WB_alu_result);

        $display("\n====================  MEM_WB_Register Test END  ====================");

        $stop;
    end

endmodule

RV32I/testbenches/results/waveforms/MEM_WB_Register_tb_result.vcd
$date
	Fri May 23 23:48:57 2025
$end
$version
	Icarus Verilog
$end
$timescale
	1ps
$end
$scope module MEM_WB_Register_tb $end
$scope module mem_wb_register $end
$var wire 32 ! MEM_alu_result [31:0] $end
$var wire 32 " MEM_csr_read_data [31:0] $end
$var wire 1 # MEM_csr_write_enable $end
$var wire 32 $ MEM_imm [31:0] $end
$var wire 32 % MEM_pc_plus_4 [31:0] $end
$var wire 5 & MEM_rd [4:0] $end
$var wire 32 ' MEM_register_file_write_data [31:0] $end
$var wire 3 ( MEM_register_file_write_data_select [2:0] $end
$var wire 1 ) MEM_register_write_enable $end
$var wire 1 * clk $end
$var wire 1 + flush $end
$var wire 1 , reset $end
$var parameter 32 - XLEN $end
$var reg 32 . WB_alu_result [31:0] $end
$var reg 32 / WB_csr_read_data [31:0] $end
$var reg 1 0 WB_csr_write_enable $end
$var reg 32 1 WB_imm [31:0] $end
$var reg 32 2 WB_pc_plus_4 [31:0] $end
$var reg 5 3 WB_rd [4:0] $end
$var reg 32 4 WB_register_file_write_data [31:0] $end
$var reg 3 5 WB_register_file_write_data_select [2:0] $end
$var reg 1 6 WB_register_write_enable $end
$upscope $end
$upscope $end
$enddefinitions $end
$comment Show the parameter values. $end
$dumpall
b100000 -
$end
#0
$dumpvars
06
b0 5
b0 4
b0 3
b0 2
b0 1
00
b0 /
b0 .
1,
0+
0*
x)
bx (
bx '
bx &
bx %
bx $
x#
bx "
bx !
$end
#5000
1*
#10000
0*
#15000
1*
#20000
0*
#25000
1*
#30000
0*
0,
#35000
bx 4
bx 3
x0
x6
bx .
bx /
bx 1
bx 5
bx 2
1*
#40000
0*
#45000
1*
#50000
b1010 '
b110 &
0#
1)
b1011 !
b0 "
b0 $
b10 (
b100 %
0*
#55000
b1010 4
b110 3
00
16
b1011 .
b0 /
b0 1
b10 5
b100 2
1*
#60000
0*
#65000
1*
#70000
b11011110101011011011111011101111 '
b111 &
b10000000000000000000000100000 !
b100000 $
b1 (
b1000 %
0*
#75000
b11011110101011011011111011101111 4
b111 3
b10000000000000000000000100000 .
b100000 1
b1 5
b1000 2
1*
#76000
1+
#80000
0*
#85000
b0 4
b0 3
06
b0 .
b0 1
b0 5
b0 2
1*
#86000
b11001010111111101011101010111110 '
b10001 &
1#
b0 !
b11001010111111101011101010111110 "
b0 $
b11 (
b1100 %
0+
#90000
0*
#95000
b11001010111111101011101010111110 4
b10001 3
10
16
b11001010111111101011101010111110 /
b11 5
b1100 2
1*
