RV32I/modules/PC_Controller.v
module PCController (
    input jump, 				// signal indicating if PC should jump
	input branch_taken,			// signal indicating if PC should take the branch
	input trapped,				// signal indicating if trap has occurred
	input [31:0] pc,			// current pc value
	input [31:0] jump_target,	// target address for jump
	input [31:0] imm,			// immediate value from Immediate Generator
	input [31:0] trap_target,	// target address for trap
	input pc_stall,				// signal indicating if pc update should be paused

	output reg [31:0] next_pc	// next pc value
);

    always @(*) begin
		if (pc_stall) begin
			next_pc = pc;
		end
		else if (jump && pc_stall == 0 && trapped == 0 && branch_taken == 0) begin
			next_pc = jump_target;
		end
		else if (branch_taken && jump == 0 && pc_stall == 0 && trapped == 0) begin
			next_pc = pc + imm;
		end
		else if (trapped && jump == 0 && pc_stall == 0 && branch_taken == 0) begin
			next_pc = trap_target;
		end
		else begin
			next_pc = pc + 4;
		end
	end

endmodule

RV32I/testbenches/PC_Controller_tb.v
`timescale 1ns/1ps

module PCController_tb;
    reg jump;
    reg branch_taken;
    reg trapped;
    reg [31:0] pc;
    reg [31:0] jump_target;
    reg [31:0] imm;
    reg [31:0] trap_target;
	reg pc_stall;

    wire [31:0] next_pc;

    PCController pc_controller (
        .jump(jump),
        .branch_taken(branch_taken),
        .trapped(trapped),
        .pc(pc),
        .jump_target(jump_target),
        .imm(imm),
        .trap_target(trap_target),
		.pc_stall(pc_stall),

        .next_pc(next_pc)
    );

    initial begin
        $dumpfile("testbenches/results/waveforms/PC_Controller_tb_result.vcd");
        $dumpvars(0, pc_controller);

		// Test sequence
        $display("==================== PCController Test START ====================");

        pc = 32'b0;
        jump_target = 32'b0;
        imm = 32'b0;
        trap_target = 32'b0;

        // Test 1: Pause PC update
        $display("\nPause PC update: ");

        pc_stall = 1;

        jump = 1;
        branch_taken = 0;
        trapped = 0;

        jump_target = 32'h12345678;

        #10;
        $display("pc = %h => next_pc = %h", pc, next_pc);

        jump_target = 32'b0;

        // Test 2: No jump, no branch, no trap
        $display("\nNo jump, No branch, No trap: ");

        pc_stall = 0;

        jump = 0;
        branch_taken = 0;
        trapped = 0;

        #10;
        $display("pc = %h => next_pc = %h", pc, next_pc);

        // Test 3: Jump
		$display("\nJump: ");
		
        pc = next_pc;

        jump = 1;
		branch_taken = 0;
		trapped = 0;

        jump_target = 32'hDEAD0000;
		
        #10;
        $display("pc = %h => next_pc = %h", pc, next_pc);

        // Test 4: Branch taken
        $display("\nBranch taken: ");
        
        pc = next_pc;

		jump = 0;
		branch_taken = 1;
		trapped = 0;

        imm = 32'h0000BEEF;
		
        #10;
        $display("pc = %h => next_pc = %h", pc, next_pc);

        // Test 5: Trapped
        $display("\nTrapped: ");
        
        pc = next_pc;

		jump = 0;
		branch_taken = 0;
		trapped = 1;
		
        trap_target = 32'hCAFEBABE;

        #10;
        $display("pc = %h => next_pc = %h", pc, next_pc);

        // Test 6: Normal increment
        $display("\nNormal increment: ");
        
        pc = 32'h00001000;

		jump = 0;
		branch_taken = 0;
		trapped = 0;
		
        #10;
        $display("pc = %h => next_pc = %h", pc, next_pc);

        // Test 7: Race condition
        $display("\nRace condition: ");
        
        pc = 32'h00001000;

		jump = 1;
        #1;
        $display("pc = %h => next_pc = %h", pc, next_pc);
        pc_stall = 1;
        #1;
        $display("pc = %h => next_pc = %h", pc, next_pc);
		branch_taken = 0;
		trapped = 1;
        #1;
        $display("pc = %h => next_pc = %h", pc, next_pc);

        pc_stall = 0;
        #1;
        $display("pc = %h => next_pc = %h", pc, next_pc);

        #10;
        $display("pc = %h => next_pc = %h", pc, next_pc);

        $display("\n====================  PCController Test END  ====================");
        $stop;
    end

endmodule

RV32I/testbenches/results/waveforms/PC_Controller_tb_result.vcd
$date
	Thu May 15 22:09:15 2025
$end
$version
	Icarus Verilog
$end
$timescale
	1ps
$end
$scope module PCController_tb $end
$scope module pc_controller $end
$var wire 1 ! branch_taken $end
$var wire 32 " imm [31:0] $end
$var wire 1 # jump $end
$var wire 32 $ jump_target [31:0] $end
$var wire 32 % pc [31:0] $end
$var wire 1 & pc_stall $end
$var wire 32 ' trap_target [31:0] $end
$var wire 1 ( trapped $end
$var reg 32 ) next_pc [31:0] $end
$upscope $end
$upscope $end
$enddefinitions $end
$comment Show the parameter values. $end
$dumpall
$end
#0
$dumpvars
b0 )
0(
b0 '
1&
b0 %
b10010001101000101011001111000 $
1#
b0 "
0!
$end
#10000
b100 )
0#
0&
b0 $
#20000
b11011110101011010000000000000000 )
b11011110101011010000000000000000 $
1#
b100 %
#30000
b11011110101011011011111011101111 )
b1011111011101111 "
1!
0#
b11011110101011010000000000000000 %
#40000
b11001010111111101011101010111110 )
b11001010111111101011101010111110 '
1(
0!
b11011110101011011011111011101111 %
#50000
b1000000000100 )
0(
b1000000000000 %
#60000
b11011110101011010000000000000000 )
1#
#61000
b1000000000000 )
1&
#62000
1(
#63000
b1000000000100 )
0&
