RV32I/modules/Trap_Controller.v
  `include "modules/headers/trap.vh"

module TrapController (
    input wire        clk,
    input wire        rst,
    input wire [31:0] pc,
    input wire [2:0]  trap_status,
    input wire [31:0] csr_read_data,

    output reg [31:0] trap_target,
    output reg        ic_clean,
    output reg        debug_mode,
    output reg [11:0] csr_trap_address,
    output reg [31:0] csr_trap_write_data,
    output reg        trap_done
);

localparam  IDLE          = 2'b00,
            WRITE_MEPC    = 2'b01,
            WRITE_MCAUSE  = 2'b10,
            READ_MTVEC    = 2'b11;
            
reg [1:0] trap_handle_state;

always @(posedge clk or posedge rst) begin
    //reset
    if (rst) begin
        trap_handle_state    <= IDLE;
        debug_mode           <= 1'b0;
        ic_clean             <= 1'b0;
        trap_target          <= 32'b0;
        csr_trap_address     <= 12'b0;
        csr_trap_write_data  <= 32'b0;
        trap_done            <= 1'b1;
    end else begin
    // prevent latch synthesis (default value allocation)
        debug_mode           <= 1'b0;
        ic_clean             <= 1'b0;
        csr_trap_address     <= 12'b0;
        csr_trap_write_data  <= 32'b0;
        trap_target          <= 32'b0;
        trap_done            <= 1'b1;

    case (trap_status)
        `TRAP_EBREAK: begin
            trap_done  <= 1'b0;
            debug_mode <= 1'b1;
            case (trap_handle_state)
            //Write mepc mode
                IDLE: begin
                    csr_trap_address    <= 12'h341;     //mepc
                    csr_trap_write_data <= pc;
                    trap_handle_state   <= WRITE_MEPC;
            end
            //Write mcause mode
                WRITE_MEPC: begin
                    csr_trap_address    <= 12'h342; //mcause
                    csr_trap_write_data <= 32'd3; //mcause value 3 = Breakpoint exception code
                    trap_handle_state   <= WRITE_MCAUSE;
            end
            //Pre-Trap Handling done state
                WRITE_MCAUSE: begin
                    trap_done <= 1'b1;
            end
            endcase
        end
        
        `TRAP_ECALL: begin
            trap_done <= 1'b0;
            case (trap_handle_state)
            //Write mepc mode
                IDLE: begin
                    csr_trap_address    <= 12'h341;     //mepc
                    csr_trap_write_data <= pc;
                    trap_handle_state   <= WRITE_MEPC;
            end
            //Write mcause mode
                WRITE_MEPC: begin
                    csr_trap_address    <= 12'h342; //mcause
                    csr_trap_write_data <= 32'd11; //mcause value 11 = Environment call from M-mode exception code
                    trap_handle_state   <= WRITE_MCAUSE;
            end
            //Read mtvec mode
                WRITE_MCAUSE: begin
                    csr_trap_address  <= 12'h305; //mtvec
                    trap_target       <= csr_read_data;
                    trap_handle_state <= READ_MTVEC;
            end
            //Pre-Trap Handling done state
                READ_MTVEC: begin
                    trap_done <= 1'b1;
            end
            endcase
        end

        `TRAP_MISALIGNED: begin
            trap_done  <= 1'b0;
            case (trap_handle_state)
            //Write mepc mode
                IDLE: begin
                    trap_done           <= 1'b0;
                    csr_trap_address    <= 12'h341;     //mepc
                    csr_trap_write_data <= pc;
                    trap_handle_state   <= WRITE_MEPC;
            end
            //Write mcause mode
                WRITE_MEPC: begin
                    csr_trap_address    <= 12'h342; //mcause
                    csr_trap_write_data <= 32'd0; //mcause value 0 = Instruction address misaligned exception code
                    trap_handle_state   <= WRITE_MCAUSE;
            end
            //Read mtvec mode
                WRITE_MCAUSE: begin
                    csr_trap_address  <= 12'h305; //mtvec
                    trap_target       <= csr_read_data;
                    trap_handle_state <= READ_MTVEC;
                end
            //Pre-Trap Handling done state
                READ_MTVEC: begin
                    trap_done <= 1'b1;
            end
            endcase
        end

        `TRAP_FENCEI: begin
            ic_clean  <= 1'b1;
            trap_done <= 1'b1;
        end

        `TRAP_MRET: begin
            csr_trap_address   <= 12'h341; //mepc
            trap_target        <= csr_read_data + 4;
            debug_mode         <= 1'b0;
            trap_handle_state  <= IDLE;
            trap_done          <= 1'b1;
        end

        `TRAP_NONE: begin
            ic_clean          <= 1'b0;
            debug_mode        <= 1'b0;
            trap_handle_state <= IDLE;
            trap_done         <= 1'b1;
        end
    endcase
end
end

endmodule

RV32I/testbenches/Trap_Controller_tb.v
`timescale 1ns/1ps
`include "modules/headers/trap.vh"

module TrapController_tb;
  // Signal Declaration
  reg         clk;
  reg         rst;
  reg  [31:0] pc;
  reg  [2:0]  trap_status;
  reg  [31:0] csr_read_data;

  wire [31:0] trap_target;
  wire        ic_clean;
  wire        debug_mode;
  wire        trap_done;
  wire [11:0] csr_trap_address;
  wire [31:0] csr_trap_write_data;

  // DUT instance
  TrapController trap_controller (
    .clk                (clk),
    .rst                (rst),
    .pc                 (pc),
    .trap_status        (trap_status),
    .csr_read_data      (csr_read_data),

    .trap_target        (trap_target),
    .ic_clean           (ic_clean),
    .debug_mode         (debug_mode),
    .csr_trap_address   (csr_trap_address),
    .csr_trap_write_data(csr_trap_write_data),
    .trap_done          (trap_done)
  );

  // Generate clock signal (period = 10ns)
  initial clk = 0;
  always #5 clk = ~clk;

  // VCD dump
  initial begin
    $dumpfile("testbenches/results/waveforms/Trap_Controller_tb_result2.vcd");
    $dumpvars(0, TrapController_tb);
  end

  // Monitor setup :  internal state, CSR Read/Write, output changes
  initial begin
    $display("time | th_state | csr_addr | csr_wd | trap_tgt  | ic_clean | debug | trap_done");
    $monitor("%4t |  %b   |   %h   |    %h    |   %h   |     %b    |   %b   |  %b  |",
             $time,
             trap_controller.trap_handle_state,
             csr_trap_address,
             csr_trap_write_data,
             trap_target,
             ic_clean,
             debug_mode,
             trap_done);
  end

  // Testbench
  initial begin
    $display("==================== Register File Test START ====================");
    // Initialize signals
    rst          = 1;
    trap_status  = `TRAP_NONE;
    pc           = 32'h0000_0000;
    csr_read_data= 32'h0000_0000;
    #20 rst = 0;

    // ── ECALL Test ──
    pc           = 32'h0000_1100;
    trap_status  = `TRAP_ECALL;
    // mtvec base address = 1000_AA00
    #25; csr_read_data = 32'h1000_AA00;
    #30;

    /* expected values
    CSR_T.Addr = 12'h341
    CSR_T.WD = 0000_1100
    trap_handle_state = IDLE -> WRITE_MEPC

    CSR_T.Addr = 12'h342
    CSR_T.WD = 32'd11
    trap_handle_state = WRITE_MEPC -> WRITE_MCAUSE

    trap_target = 1000_AA00
    */

    // ── MRET Test ──
    // Assumes that mepc already has the value
    trap_status   = `TRAP_MRET;
    csr_read_data = 32'h0000_1100;  // mepc
    #10;
    /* expected values
    CSR_T.Addr = 12'h341
    trap_target = 32'h0000_1104
    debug_mode = 0
    trap_handle_state = IDLE
    */

    // ── MISALIGNED Test ──
    pc           = 32'h0000_1111;
    trap_status   = `TRAP_MISALIGNED;
    // mtvec, go to trap_handler address
    csr_read_data = 32'h1000_AA00; 
    #30;
    // expected trap_target = 1000_AA00
    // mepc = 0000_1111
    // mcause = 32'd0

    // ── MRET Test ──
    // Assumes that mepc already has the value
    trap_status   = `TRAP_MRET;
    csr_read_data = 32'h0000_1110;  // mepc
    #10;
    /* expected values
    CSR_T.Addr = 12'h341
    trap_target = 32'h0000_1114
    debug_mode = 0
    trap_handle_state = IDLE
    */

    // ── EBREAK Test ──
    pc           = 32'h0000_BBB0;
    trap_status  = `TRAP_EBREAK;
    #20;
    // expected debug_mode = 1
    // mepc = 0000_BBB0
    // mcause = 32'd3

    // ── MRET Test ──
    // Assumes that mepc already has the value
    trap_status   = `TRAP_MRET;
    csr_read_data = 32'h0000_BBB0;  // mepc
    #10;
    /* expected values
    CSR_T.Addr = 12'h341
    trap_target = 32'h0000_BBB4
    debug_mode = 0
    trap_handle_state = IDLE
    */

    // ── FENCE.I Test ──
    trap_status = `TRAP_FENCEI;
    #10;
    // expected ic_clean <= 1'b1

    // ── NONE Test ──
    trap_status = `TRAP_NONE;
    #10;
    $display("\n====================  Register File Test END  ====================");
    $finish;
  end
endmodule

RV32I/testbenches/results/waveforms/Trap_Controller_tb_result2.vcd
$date
	Fri May 09 22:48:24 2025
$end
$version
	Icarus Verilog
$end
$timescale
	1ps
$end
$scope module TrapController_tb $end
$var wire 32 ! trap_target [31:0] $end
$var wire 1 " trap_done $end
$var wire 1 # ic_clean $end
$var wire 1 $ debug_mode $end
$var wire 32 % csr_trap_write_data [31:0] $end
$var wire 12 & csr_trap_address [11:0] $end
$var reg 1 ' clk $end
$var reg 32 ( csr_read_data [31:0] $end
$var reg 32 ) pc [31:0] $end
$var reg 1 * rst $end
$var reg 3 + trap_status [2:0] $end
$scope module trap_controller $end
$var wire 1 ' clk $end
$var wire 32 , csr_read_data [31:0] $end
$var wire 32 - pc [31:0] $end
$var wire 1 * rst $end
$var wire 3 . trap_status [2:0] $end
$var parameter 2 / IDLE $end
$var parameter 2 0 READ_MTVEC $end
$var parameter 2 1 WRITE_MCAUSE $end
$var parameter 2 2 WRITE_MEPC $end
$var reg 12 3 csr_trap_address [11:0] $end
$var reg 32 4 csr_trap_write_data [31:0] $end
$var reg 1 $ debug_mode $end
$var reg 1 # ic_clean $end
$var reg 1 " trap_done $end
$var reg 2 5 trap_handle_state [1:0] $end
$var reg 32 6 trap_target [31:0] $end
$upscope $end
$upscope $end
$enddefinitions $end
$comment Show the parameter values. $end
$dumpall
b1 2
b10 1
b11 0
b0 /
$end
#0
$dumpvars
b0 6
b0 5
b0 4
b0 3
b0 .
b0 -
b0 ,
b0 +
1*
b0 )
b0 (
0'
b0 &
b0 %
0$
0#
1"
b0 !
$end
#5000
1'
#10000
0'
#15000
1'
#20000
0'
b10 +
b10 .
b1000100000000 )
b1000100000000 -
0*
#25000
b1 5
b1000100000000 %
b1000100000000 4
b1101000001 &
b1101000001 3
0"
1'
#30000
0'
#35000
b10 5
0"
b1011 %
b1011 4
b1101000010 &
b1101000010 3
1'
#40000
0'
#45000
b11 5
b10000000000001010101000000000 !
b10000000000001010101000000000 6
0"
b0 %
b0 4
b1100000101 &
b1100000101 3
1'
b10000000000001010101000000000 (
b10000000000001010101000000000 ,
#50000
0'
#55000
1"
b0 !
b0 6
b0 &
b0 3
1'
#60000
0'
#65000
1"
1'
#70000
0'
#75000
b0 5
b1000100000100 !
b1000100000100 6
b1101000001 &
b1101000001 3
1'
b1000100000000 (
b1000100000000 ,
b100 +
b100 .
#80000
0'
#85000
b1 5
b1000100010001 %
b1000100010001 4
0"
b0 !
b0 6
b1101000001 &
b1101000001 3
1'
b10000000000001010101000000000 (
b10000000000001010101000000000 ,
b11 +
b11 .
b1000100010001 )
b1000100010001 -
#90000
0'
#95000
b10 5
0"
b0 %
b0 4
b1101000010 &
b1101000010 3
1'
#100000
0'
#105000
b11 5
b10000000000001010101000000000 !
b10000000000001010101000000000 6
0"
b1100000101 &
b1100000101 3
1'
#110000
0'
#115000
b0 5
1"
b1000100010100 !
b1000100010100 6
b1101000001 &
b1101000001 3
1'
b1000100010000 (
b1000100010000 ,
b100 +
b100 .
#120000
0'
#125000
b1 5
b1011101110110000 %
b1011101110110000 4
1$
0"
b0 !
b0 6
b1101000001 &
b1101000001 3
1'
b1 +
b1 .
b1011101110110000 )
b1011101110110000 -
#130000
0'
#135000
b10 5
0"
b11 %
b11 4
b1101000010 &
b1101000010 3
1$
1'
#140000
0'
#145000
b0 5
b1011101110110100 !
b1011101110110100 6
1"
b0 %
b0 4
b1101000001 &
b1101000001 3
0$
1'
b1011101110110000 (
b1011101110110000 ,
b100 +
b100 .
#150000
0'
#155000
1#
b0 !
b0 6
b0 &
b0 3
1'
b101 +
b101 .
#160000
0'
#165000
0#
1'
b0 +
b0 .
